{"sections":{"custom_liquid_aLrwHi":{"type":"custom-liquid","settings":{"full_width":true,"remove_vertical_spacing":true,"remove_horizontal_spacing":true,"liquid":"{% if product.images.size > 0 %}\n  <div id=\"best-seller-badge\" class=\"best-seller-badge\" style=\"position: absolute; top: 15px; left: 15px; z-index: 5; pointer-events: none;\">\n    <div style=\"background-color: #F0E7FF; padding: 2px 10px; border-radius: 6px; box-shadow: 0 1px 3px 0 rgba(0, 0, 0, 0.1), 0 1px 2px 0 rgba(0, 0, 0, 0.06); border: 1px solid #342c40;\">\n      <span style=\"color: #342c40; font-weight: bold; font-size: 12px;\">\n        MEILLEUR VENTE\n      <\/span>\n    <\/div>\n  <\/div>\n\n  <style>\n    @media (min-width: 768px) {\n      .best-seller-badge {\n        display: none;\n      }\n    }\n    .product-gallery__media-list-wrapper {\n      position: relative;\n    }\n    .product-gallery__media-list-wrapper .best-seller-badge {\n      position: absolute;\n      z-index: 5;\n    }\n  <\/style>\n\n  <script>\n    document.addEventListener('DOMContentLoaded', function() {\n      var badge = document.getElementById('best-seller-badge');\n      var mediaListWrapper = document.querySelector('.product-gallery__media-list-wrapper');\n      \n      if (mediaListWrapper && badge) {\n        mediaListWrapper.appendChild(badge);\n        \n        var firstImage = mediaListWrapper.querySelector('.product-gallery__media');\n        if (firstImage) {\n          var observer = new IntersectionObserver(function(entries) {\n            entries.forEach(function(entry) {\n              badge.style.display = entry.isIntersecting ? 'block' : 'none';\n            });\n          }, { threshold: 0.5, root: null });\n\n          observer.observe(firstImage);\n        }\n      }\n    });\n  <\/script>\n{% endif %}","background":"","background_gradient":"","text_color":""}},"main":{"type":"main-product","blocks":{"liquid_c7QkwC":{"type":"liquid","settings":{"liquid":"<div class=\"reviews-luma\">\n  <div class=\"rating-badge\">\n    <div class=\"stars\">\n      <svg class=\"star\" viewBox=\"0 0 36 36\" fill=\"currentColor\">\n        <path d=\"M18 4.5L22.5 13.5L32.5 15L25.25 22L27 32L18 27.5L9 32L10.75 22L3.5 15L13.5 13.5L18 4.5Z\"><\/path>\n      <\/svg>\n      <svg class=\"star\" viewBox=\"0 0 36 36\" fill=\"currentColor\">\n        <path d=\"M18 4.5L22.5 13.5L32.5 15L25.25 22L27 32L18 27.5L9 32L10.75 22L3.5 15L13.5 13.5L18 4.5Z\"><\/path>\n      <\/svg>\n      <svg class=\"star\" viewBox=\"0 0 36 36\" fill=\"currentColor\">\n        <path d=\"M18 4.5L22.5 13.5L32.5 15L25.25 22L27 32L18 27.5L9 32L10.75 22L3.5 15L13.5 13.5L18 4.5Z\"><\/path>\n      <\/svg>\n      <svg class=\"star\" viewBox=\"0 0 36 36\" fill=\"currentColor\">\n        <path d=\"M18 4.5L22.5 13.5L32.5 15L25.25 22L27 32L18 27.5L9 32L10.75 22L3.5 15L13.5 13.5L18 4.5Z\"><\/path>\n      <\/svg>\n      <svg class=\"star last-star\" viewBox=\"0 0 36 36\">\n        <defs>\n          <linearGradient id=\"partialFill\" x1=\"0%\" y1=\"0%\" x2=\"100%\" y2=\"0%\">\n            <stop offset=\"0%\" stop-color=\"#9f87c7\" \/>\n            <stop offset=\"65%\" stop-color=\"#9f87c7\" \/>\n            <stop offset=\"65%\" stop-color=\"#f7f7f7\" \/>\n            <stop offset=\"100%\" stop-color=\"#f7f7f7\" \/>\n          <\/linearGradient>\n        <\/defs>\n        <path d=\"M18 4.5L22.5 13.5L32.5 15L25.25 22L27 32L18 27.5L9 32L10.75 22L3.5 15L13.5 13.5L18 4.5Z\" fill=\"url(#partialFill)\"><\/path>\n      <\/svg>\n    <\/div>\n    <span class=\"rating\">4.7<\/span>\n    <span class=\"separator\">|<\/span>\n    <span class=\"reviews\">+5000 AVIS VÉRIFIÉS<\/span>\n  <\/div>\n\n  <style>\n    .rating-badge {\n      background-color: #f0e7ff;\n      padding: 3px 10px;\n      border-radius: 6px;\n      display: flex;\n      align-items: center;\n      gap: 6px;\n      color: #342c40;\n      max-width: fit-content;\n      font-family: 'Poppins', sans-serif;\n      font-weight: 500;\n      transform: scale(0.9);\n      transform-origin: left center; \n    }\n    .stars {\n      display: flex;\n      gap: -2px;\n      align-items: center;\n    }\n\n    .star {\n      width: 20px;\n      height: 25px;\n      color: #9f87c7;\n    }\n\n    .rating {\n      font-weight: 800;\n      margin-left: 2px;\n      font-size: 15px;\n    }\n\n    .separator {\n      color: #342c40;\n    }\n\n    .reviews {\n      font-weight: 600;\n      color: #342c40;\n      font-size: 15px;\n      letter-spacing: -0.2px;\n    }\n\n    @media (max-width: 425px) {\n      .rating-badge {\n        background-color: #f0e7ff;\n        padding: 3px 10px;\n        border-radius: 6px;\n        display: flex;\n        align-items: center;\n        gap: 6px;\n        color: #342c40;\n        max-width: fit-content;\n        font-family: 'Poppins', sans-serif;\n        font-weight: 500;\n        transform: scale(0.8);\n        transform-origin: left center;\n      }\n    }\n  <\/style>\n<\/div>"}},"liquid_paEeai":{"type":"liquid","settings":{"liquid":"<style>\n  .title-luma h1 {\n    font-family: 'Poppins', sans-serif;\n    font-weight: 600;\n    color: #342c40;\n    text-transform: uppercase;\n    font-size: 35px;\n    letter-spacing: -1px;\n    margin-bottom: 10px;\n    margin-top: -25px;\n  }\n\n  @media (max-width: 383px) {\n    .title-luma h1 {\n      font-size: 31px; \n      letter-spacing: -0.5px; \n      margin-top: -25px; \n    }\n  }\n<\/style>\n\n<div class=\"title-luma\">\n  <h1>LUMA LINEA EYELINER<\/h1>\n<\/div>"}},"liquid_HEHgPM":{"type":"liquid","settings":{"liquid":"<style>\n  .description-luma p {\n    font-family: 'Poppins', sans-serif;\n    font-weight: 300; \n    color: #342c40;\n    font-size: 16px;\n    line-height: 1.3;\n    margin: 0;\nmargin-top: -30px;\n  }\n\n  .description-luma strong {\n    font-weight: 500; \n  }\n\n  @media (max-width: 383px) {\n    .description-luma p {\n      font-size: 14px;\n      line-height: 1.2;\n    }\n  }\n<\/style>\n\n<link href=\"https:\/\/fonts.googleapis.com\/css2?family=Poppins:wght@300;500&display=swap\" rel=\"stylesheet\">\n\n<div class=\"description-luma\">\n  <p>Le premier <strong>eyeliner<\/strong> pensé pour les paupières <strong>matures<\/strong> : application <strong>douce<\/strong>, tracé <strong>net<\/strong> et tenue <strong>24h sans bavure<\/strong>.<\/p>\n<\/div>"}},"liquid_WAFHrP":{"type":"liquid","settings":{"liquid":"<style>\n  .features-list {\n    margin-top: -5px;\n    padding: 0;\n    list-style: none;\n    max-width: 100%;\n  }\n\n  .features-list li {\n    display: flex;\n    align-items: center;\n    gap: 15px;\n    margin-bottom: 10px;\n    font-family: 'Poppins', sans-serif;\n    font-weight: 400;\n    color: #342c40;\n    font-size: 16px;\n    line-height: 1.4;\n  }\n\n  .features-list .text-wrapper {\n    flex: 1;\n    min-width: 0;\n    max-width: calc(100% - 50px); \n    padding-right: 20px;\n  }\n\n  .features-list p {\n    margin: 0;\n    text-wrap: pretty;\n    word-spacing: normal;\n    hyphens: auto;\n  }\n\n  .features-list img {\n    width: 35px;\n    height: auto;\n    flex-shrink: 0;\n    margin-top: 5px;\n  }\n\n  .features-list strong {\n    font-weight: 600;\n    color: #9f87c7;\n    white-space: nowrap;\n  }\n\n  @media (max-width: 383px) {\n    .features-list li {\n      font-size: 14px;\n      gap: 10px;\n      margin-bottom: 10px;\n    }\n\n    .features-list img {\n      width: 30px;\n    }\n\n    .features-list .text-wrapper {\n      max-width: calc(100% - 40px); \n      padding-right: 10px; \n    }\n  }\n<\/style>\n\n<link href=\"https:\/\/fonts.googleapis.com\/css2?family=Poppins:wght@400;600&display=swap\" rel=\"stylesheet\">\n\n<ul class=\"features-list\">\n  <li>\n    <img src=\"https:\/\/cdn.shopify.com\/s\/files\/1\/0924\/0848\/0091\/files\/ICON_1.webp?v=1740143284\" alt=\"\" aria-hidden=\"true\">\n    <div class=\"text-wrapper\">\n      <p>Une application <strong>ultra facile<\/strong> & précise - <strong>même<\/strong> sur peau ridé.<\/p>\n    <\/div>\n  <\/li>\n  <li>\n    <img src=\"https:\/\/cdn.shopify.com\/s\/files\/1\/0924\/0848\/0091\/files\/ICON_4.webp?v=1740143284\" alt=\"\" aria-hidden=\"true\">\n    <div class=\"text-wrapper\">\n      <p>Texture gel crème <strong>douce<\/strong> & crémeuse - <strong>zéro<\/strong> tiraillement.<\/p>\n    <\/div>\n  <\/li>\n  <li>\n    <img src=\"https:\/\/cdn.shopify.com\/s\/files\/1\/0924\/0848\/0091\/files\/ICON_2.webp?v=1740143284\" alt=\"\" aria-hidden=\"true\">\n    <div class=\"text-wrapper\">\n      <p>Résiste à l'eau et l'humidité mais s'enlève <strong>sans effort<\/strong>.<\/p>\n    <\/div>\n  <\/li>\n  <li>\n    <img src=\"https:\/\/cdn.shopify.com\/s\/files\/1\/0924\/0848\/0091\/files\/ICON_3.webp?v=1740143283\" alt=\"\" aria-hidden=\"true\">\n    <div class=\"text-wrapper\">\n      <p>Formule hypoallergénique - <strong>adaptée<\/strong> aux yeux sensibles.<\/p>\n    <\/div>\n  <\/li>\n<\/ul>"}},"liquid_K3BNDb":{"type":"liquid","settings":{"liquid":"<style>\n  .testimonial-module .testimonial-container-reviews {\n    position: relative;\n    background-color: #f0e7ff;\n    border-radius: 15px;\n    padding: 15px;\n    max-width: 600px;\n    width: 100%;\n    box-sizing: border-box;\n  }\n\n  .testimonial-module .badge-top-right-reviews {\n    position: absolute;\n    top: -45px;\n    right: -5px;\n    width: 95px;\n    height: auto;\n    z-index: 2;\n  }\n\n  .testimonial-module .testimonial-content-reviews {\n    display: flex;\n    align-items: flex-start;\n  }\n\n  .testimonial-module .profile-image-reviews {\n    width: 20px; \n    height: 20px;\n    border-radius: 8px;\n    object-fit: cover;\n    flex-shrink: 0;\n  }\n\n  .testimonial-module .testimonial-text-reviews {\n    flex: 1;\n  }\n\n  .testimonial-module .rating-badge-reviews {\n    margin-bottom: 5px;\n    margin-top: -6px;\n  }\n\n  .testimonial-module .rating-badge-reviews .star-reviews {\n    display: flex;\n  }\n\n  .testimonial-module .rating-badge-reviews .star-reviews svg {\n    width: 25px;\n    height: 25px;\n    color: #9f87c7;\n  }\n\n  .testimonial-module .quote-reviews {\n    font-family: 'Poppins', sans-serif;\n    font-style: italic;\n    font-weight: 400;\n    color: #342c40;\n    font-size: 15px;\n    line-height: 1.3;\n    margin-bottom: 12px;\n  }\n\n  .testimonial-module .author-info-reviews {\n    display: flex;\n    align-items: center;\n    gap: 10px;\n  }\n\n  .testimonial-module .author-name-reviews {\n    font-family: 'Poppins', sans-serif;\n    font-weight: 500;\n    color: #342c40;\n    font-size: 14px;\n  }\n\n  .testimonial-module .verified-badge-reviews {\n    background-color: #342c40;\n    color: white;\n    font-family: 'Poppins', sans-serif;\n    font-size: 10px;\n    padding: 3px 6px;\n    border-radius: 4px;\n    font-weight: 400;\n  }\n\n  @media (max-width: 383px) {\n    .testimonial-module .testimonial-content-reviews {\n      flex-direction: column;\n      gap: 15px;\n    }\n\n    .testimonial-module .profile-image-reviews {\n      width: 40px;\n      height: 40px;\n    }\n\n    .testimonial-module .quote-reviews {\n      font-size: 13px;\n    }\n\n    .testimonial-module .author-name-reviews {\n      font-size: 14px;\n    }\n\n    .testimonial-module .badge-top-right-reviews {\n      width: 80px;\n        top: -40px;\n        right: -5px;\n    }\n\n    .testimonial-module .rating-badge-reviews .star-reviews svg {\n      width: 18px;\n      height: 18px;\n    }\n  }\n<\/style>\n\n<link href=\"https:\/\/fonts.googleapis.com\/css2?family=Poppins:ital,wght@0,400;1,400&display=swap\" rel=\"stylesheet\">\n\n<div class=\"testimonial-module\">\n  <div class=\"testimonial-container-reviews\">\n    <img src=\"https:\/\/cdn.shopify.com\/s\/files\/1\/0924\/0848\/0091\/files\/BADGE_N1_EYELINER_V2.webp?v=1740145102\" alt=\"Badge\" class=\"badge-top-right-reviews\">\n    \n    <div class=\"testimonial-content-reviews\">\n      <div class=\"testimonial-text-reviews\">\n        <div class=\"rating-badge-reviews\">\n          <div class=\"star-reviews\">\n            <svg viewBox=\"0 0 36 36\" fill=\"currentColor\">\n              <path d=\"M18 4.5L22.5 13.5L32.5 15L25.25 22L27 32L18 27.5L9 32L10.75 22L3.5 15L13.5 13.5L18 4.5Z\"><\/path>\n            <\/svg>\n            <svg viewBox=\"0 0 36 36\" fill=\"currentColor\">\n              <path d=\"M18 4.5L22.5 13.5L32.5 15L25.25 22L27 32L18 27.5L9 32L10.75 22L3.5 15L13.5 13.5L18 4.5Z\"><\/path>\n            <\/svg>\n            <svg viewBox=\"0 0 36 36\" fill=\"currentColor\">\n              <path d=\"M18 4.5L22.5 13.5L32.5 15L25.25 22L27 32L18 27.5L9 32L10.75 22L3.5 15L13.5 13.5L18 4.5Z\"><\/path>\n            <\/svg>\n            <svg viewBox=\"0 0 36 36\" fill=\"currentColor\">\n              <path d=\"M18 4.5L22.5 13.5L32.5 15L25.25 22L27 32L18 27.5L9 32L10.75 22L3.5 15L13.5 13.5L18 4.5Z\"><\/path>\n            <\/svg>\n            <svg viewBox=\"0 0 36 36\" fill=\"currentColor\">\n              <path d=\"M18 4.5L22.5 13.5L32.5 15L25.25 22L27 32L18 27.5L9 32L10.75 22L3.5 15L13.5 13.5L18 4.5Z\"><\/path>\n            <\/svg>\n          <\/div>\n        <\/div>\n        \n        <p class=\"quote-reviews\">\"L'eyeliner parfait pour les paupières matures ! Il glisse en douceur, zéro tiraillement et tient toute la journée sans bavure. Enfin un maquillage qui me comprend après 50 ans !\"<\/p>\n        \n        <div class=\"author-info-reviews\">\n          <span>Caroline, 55 ans<\/span>\n          <span class=\"verified-badge-reviews\">AVIS VÉRIFIÉ<\/span>\n        <\/div>\n      <\/div>\n    <\/div>\n  <\/div>\n<\/div>"}},"liquid_nBYe6Q":{"type":"liquid","settings":{"liquid":"<div style=\"position: relative;\">\n  <a href=\"#eyeliner-section\" style=\"\n    position: absolute; \n    color: black; \n    text-decoration: underline; \n  \" class=\"teinte-link\">\n    TROUVER MA TEINTE IDÉALE\n  <\/a>\n<\/div>\n\n<style>\n  .teinte-link {\n    font-size: 15px;\n    font-weight: 500;\n    top: 0px;\n    right: 20px;\n  }\n\n \n  @media screen and (max-width: 400px) {\n    .teinte-link {\n      font-size: 14px;\n      font-weight: 500;\n      top: 1px;\n      right: 10px; \n    }\n  }\n<\/style>"}},"variant_picker_6aGVbM":{"type":"variant_picker","settings":{"hide_sold_out_variants":false,"stack_blocks":true,"selector_mode":"block","color_mode":"color","size_chart_page":""}},"liquid_LmjQXC":{"type":"liquid","settings":{"liquid":"{% render 'bundle-selector' , product: product %}"}},"liquid_HAhnH3":{"type":"liquid","settings":{"liquid":"<div class=\"better-sleep-container\">\n  <div class=\"better-sleep\">\n    <img src=\"https:\/\/cdn.shopify.com\/s\/files\/1\/0924\/0848\/0091\/files\/7823496.webp?v=1740324757\" alt=\"Guarantee icon\" width=\"10\" height=\"10\">\n    <span>GARANTIE DE REMBOURSEMENT DE 60 JOURS<\/span>\n  <\/div>\n  <div class=\"better-sleep\">\n    <img src=\"https:\/\/cdn.shopify.com\/s\/files\/1\/0924\/0848\/0091\/files\/7823496.webp?v=1740324757\" alt=\"Guarantee icon\" width=\"10\" height=\"10\">\n    <span id=\"delivery-dates\">RECEVEZ LE ENTRE LE <span id=\"date1\" class=\"underline\"><\/span> ET <span id=\"date2\" class=\"underline\"><\/span><\/span>\n  <\/div>\n<\/div>\n\n<style>\n  .better-sleep-container {\n    display: flex;\n    flex-direction: column;\n    align-items: center;\n    justify-content: center;\n    max-width: 100%;\n    margin-top: -18px;\n  }\n\n  .better-sleep {\n    display: flex;\n    align-items: center;\n    justify-content: center;\n    text-align: center;\n    padding: 7px 0;\n    width: 100%;\n  }\n\n  .better-sleep img {\n    flex-shrink: 0;\n    margin-right: 5px;\n    width: 15px;\n    height: 15px;\n  }\n\n  .better-sleep span {\n    font-size: 14px;\n    line-height: 1.1;\n  }\n\n  .underline {\n    text-decoration: underline;\n  }\n\n  @media screen and (max-width: 385px) {\n    .better-sleep span {\n      font-size: 12px;\n    }\n  }\n<\/style>\n\n<script>\n  function formatDate(date) {\n    const options = { day: 'numeric', month: 'long' };\n    return date.toLocaleDateString('fr-FR', options).toUpperCase();\n  }\n\n  function updateDates() {\n    const today = new Date();\n    const date1 = new Date(today.getTime() + 7 * 24 * 60 * 60 * 1000);\n    const date2 = new Date(today.getTime() + 9 * 24 * 60 * 60 * 1000);\n\n    document.getElementById('date1').textContent = formatDate(date1);\n    document.getElementById('date2').textContent = formatDate(date2);\n  }\n\n  \/\/ Mettre à jour les dates immédiatement et chaque jour à minuit\n  updateDates();\n  setInterval(updateDates, 24 * 60 * 60 * 1000);\n<\/script>"}},"liquid_bjjzwY":{"type":"liquid","disabled":true,"settings":{"liquid":"<div id='ss-product-videos'><\/div>"}},"image_aaGEiW":{"type":"image","settings":{"image":"shopify:\/\/shop_images\/BADGE_SITE.png","alignment":"center","max_width":500}}},"block_order":["liquid_c7QkwC","liquid_paEeai","liquid_HEHgPM","liquid_WAFHrP","liquid_K3BNDb","liquid_nBYe6Q","variant_picker_6aGVbM","liquid_LmjQXC","liquid_HAhnH3","liquid_bjjzwY","image_aaGEiW"],"settings":{"full_width":true,"show_fixed_add_to_cart":true,"desktop_media_width":50,"desktop_media_layout":"carousel_thumbnails_bottom","mobile_media_size":"expanded","mobile_carousel_control":"thumbnails","enable_video_autoplay":false,"enable_video_looping":true,"enable_image_zoom":true,"max_image_zoom_level":3,"background":"","background_gradient":"","text_color":"","input_background":"rgba(0,0,0,0)","input_text_color":""}},"custom_liquid_eHAcky":{"type":"custom-liquid","settings":{"full_width":true,"remove_vertical_spacing":false,"remove_horizontal_spacing":false,"liquid":"{% comment %}\n  Collapsible Product by Mathys - Advanced Version\n{% endcomment %}\n\n<div id=\"product-description-wrapper\" class=\"product-description-wrapper\">\n  <div id=\"custom-product-description\" class=\"product-collapsible-description\">\n    <div class=\"collapsible-wrapper\">\n      <button onclick=\"toggleSection(this)\" class=\"collapsible-item\">\n        COMMENT UTILISER LUMA LINEA\n        <svg xmlns=\"http:\/\/www.w3.org\/2000\/svg\" xmlns:xlink=\"http:\/\/www.w3.org\/1999\/xlink\" viewBox=\"0 0 100 125\" version=\"1.1\" x=\"0px\" y=\"0px\" class=\"collapsible-icon closed-icon\">\n          <g stroke=\"none\" stroke-width=\"1\" fill=\"none\" fill-rule=\"evenodd\">\n            <path d=\"M30.6378199,48.4829173 L25.6000057,55.200003 C24.9372641,56.0836584 23.6836617,56.2627444 22.8000063,55.6000029 C21.9163509,54.9372613 21.7372649,53.6836589 22.4000064,52.8000035 L27.228789,46.3616267 C24.357763,44.4286582 21.4925541,42.1288216 18.6353708,39.4621172 C17.8278696,38.7084494 17.784229,37.4428719 18.5378968,36.6353708 C19.2915645,35.8278696 20.557142,35.784229 21.3646432,36.5378968 C40.5962252,54.4873733 59.4037748,54.4873733 78.6353568,36.5378968 C79.442858,35.784229 80.7084355,35.8278696 81.4621032,36.6353708 C82.215771,37.4428719 82.1721304,38.7084494 81.3646292,39.4621172 C78.5074459,42.1288216 75.642237,44.4286582 72.771211,46.3616267 L77.5999936,52.8000035 C78.2627351,53.6836589 78.0836491,54.9372613 77.1999937,55.6000029 C76.3163383,56.2627444 75.0627359,56.0836584 74.3999943,55.200003 L69.3621801,48.4829173 C67.1747166,49.7327143 64.9843917,50.770172 62.7921776,51.5952903 L65.8569497,59.2572207 C66.2671764,60.2827875 65.7683447,61.4467281 64.7427779,61.8569548 C63.7172111,62.2671815 62.5532705,61.7683498 62.1430438,60.742783 L58.972936,52.8175136 C56.6497244,53.4301738 54.3250274,53.8047648 52,53.9412865 L52,62 C52,63.1045706 51.1045692,64 50,64 C48.8954308,64 48,63.1045706 48,62 L48,53.9412865 C45.6749726,53.8047648 43.3502756,53.4301738 41.027064,52.8175136 L37.8569562,60.742783 C37.4467295,61.7683498 36.2827889,62.2671815 35.2572221,61.8569548 C34.2316553,61.4467281 33.7328236,60.2827875 34.1430503,59.2572207 L37.2078224,51.5952903 C35.0156083,50.770172 32.8252834,49.7327143 30.6378199,48.4829173 L30.6378199,48.4829173 Z\" fill=\"#000000\" fill-rule=\"nonzero\"\/>\n          <\/g>\n        <\/svg>\n        <svg xmlns=\"http:\/\/www.w3.org\/2000\/svg\" version=\"1.1\" viewBox=\"-5.0 -10.0 110.0 135.0\" class=\"collapsible-icon open-icon\" style=\"display: none;\">\n          <path d=\"m78.195 48.906 6.4492-11.168-2.5977-1.5-6.207 10.75c-1.8398-1.4258-3.9844-2.9219-6.3867-4.3203l4.2422-11.66-2.8164-1.0273-4.0938 11.242c-1.9688-0.99219-4.0781-1.8828-6.2969-2.5938l2.1484-12.176-2.9531-0.51953-2.0977 11.887c-1.9648-0.46484-3.9961-0.77344-6.0859-0.875v-12.852h-3v12.852c-2.0898 0.10156-4.125 0.41016-6.0898 0.875l-2.0977-11.887-2.9531 0.51953 2.1484 12.176c-2.2148 0.71484-4.3242 1.6016-6.2969 2.5938l-4.0938-11.242-2.8203 1.0273 4.2422 11.66c-2.4023 1.3945-4.5469 2.8945-6.3867 4.3203l-6.207-10.75-2.5977 1.5 6.4492 11.168c-2.8164 2.4062-4.5078 4.2773-4.707 4.5l-0.88672 0.99609 0.88672 0.99609c0.60156 0.67578 14.883 16.504 32.902 16.504 18.02 0 32.301-15.828 32.902-16.504l0.88672-0.99609-0.88672-0.99609c-0.19141-0.21875-1.8828-2.0938-4.6992-4.5zm-57.898 5.5c2.3867-2.3984 9.0352-8.5312 17.664-12.004-3.0703 3.0781-4.9727 7.3242-4.9727 12.004 0 4.6758 1.8984 8.918 4.9648 11.996-8.6172-3.4727-15.27-9.6016-17.656-11.996zm29.703 14.008c-7.7266 0-14.012-6.2852-14.012-14.012 0-7.7266 6.2852-14.012 14.012-14.012s14.012 6.2852 14.012 14.012c0 7.7266-6.2852 14.012-14.012 14.012zm12.039-2.0039c3.0703-3.0781 4.9727-7.3242 4.9727-12.004 0-4.6758-1.8984-8.918-4.9648-11.996 8.6172 3.4727 15.27 9.6016 17.656 11.996-2.3867 2.3984-9.0352 8.5312-17.664 12.004z\"\/>\n          <path d=\"m54 53.332c-1.6172 0-2.9258-1.3086-2.9258-2.9258 0-1.6133 1.3047-2.9219 2.918-2.9258-1.1758-0.67969-2.5352-1.0742-3.9922-1.0742-4.418 0-8 3.582-8 8s3.582 8 8 8 8-3.582 8-8c0-1.457-0.39453-2.8164-1.0742-3.9922-0.003906 1.6133-1.3125 2.918-2.9258 2.918zm-4.6641 4.9062c-1.1055 0-2-0.89453-2-2s0.89453-2 2-2c1.1055 0 2 0.89453 2 2s-0.89844 2-2 2z\"\/>\n        <\/svg>\n      <\/button>\n      <div class=\"collapsible-content\">\n       <strong>Un regard naturel ou lifté en moins d’une minute. <\/strong>\n<br>\n<br>\n🔘 <strong> Préparez vos paupières<\/strong> <br> Nettoyez-les délicatement, puis appliquez une base et fixer l’eyeliner.<br> <br> 🔘 <strong> Posez la pointe en douceur <\/strong><br> Placez la pointe du Luma Linea Eyeliner au coin interne sans appuyer, en suivant la ligne des cils. <br> <br> 🔘 <strong> Tracez un trait modulable<\/strong><br>Faites glisser le crayon le long des cils. Pour un effet lifté, remontez légèrement vers la fin de la paupière. Repassez pour intensifier le regard. <br> <br> 🔘 <strong> Estompez ou affinez selon vos envies<\/strong> <br> Utilisez l’estompeur pour adoucir le trait si nécessaire. Cela crée un effet plus naturel.\n<br>\n<br>\n<a href=\"#etapes-section\"><strong><u>GUIDE D'ÉTAPES<\/u><\/strong><\/a>\n<br>\n<br>\n      <\/div>\n    <\/div>\n\n    <div class=\"collapsible-wrapper\">\n      <button onclick=\"toggleSection(this)\" class=\"collapsible-item\">\n        INGRÉDIENTS NATUREL\n        <svg xmlns=\"http:\/\/www.w3.org\/2000\/svg\" xmlns:xlink=\"http:\/\/www.w3.org\/1999\/xlink\" viewBox=\"0 0 100 125\" version=\"1.1\" x=\"0px\" y=\"0px\" class=\"collapsible-icon closed-icon\">\n          <g stroke=\"none\" stroke-width=\"1\" fill=\"none\" fill-rule=\"evenodd\">\n            <path d=\"M30.6378199,48.4829173 L25.6000057,55.200003 C24.9372641,56.0836584 23.6836617,56.2627444 22.8000063,55.6000029 C21.9163509,54.9372613 21.7372649,53.6836589 22.4000064,52.8000035 L27.228789,46.3616267 C24.357763,44.4286582 21.4925541,42.1288216 18.6353708,39.4621172 C17.8278696,38.7084494 17.784229,37.4428719 18.5378968,36.6353708 C19.2915645,35.8278696 20.557142,35.784229 21.3646432,36.5378968 C40.5962252,54.4873733 59.4037748,54.4873733 78.6353568,36.5378968 C79.442858,35.784229 80.7084355,35.8278696 81.4621032,36.6353708 C82.215771,37.4428719 82.1721304,38.7084494 81.3646292,39.4621172 C78.5074459,42.1288216 75.642237,44.4286582 72.771211,46.3616267 L77.5999936,52.8000035 C78.2627351,53.6836589 78.0836491,54.9372613 77.1999937,55.6000029 C76.3163383,56.2627444 75.0627359,56.0836584 74.3999943,55.200003 L69.3621801,48.4829173 C67.1747166,49.7327143 64.9843917,50.770172 62.7921776,51.5952903 L65.8569497,59.2572207 C66.2671764,60.2827875 65.7683447,61.4467281 64.7427779,61.8569548 C63.7172111,62.2671815 62.5532705,61.7683498 62.1430438,60.742783 L58.972936,52.8175136 C56.6497244,53.4301738 54.3250274,53.8047648 52,53.9412865 L52,62 C52,63.1045706 51.1045692,64 50,64 C48.8954308,64 48,63.1045706 48,62 L48,53.9412865 C45.6749726,53.8047648 43.3502756,53.4301738 41.027064,52.8175136 L37.8569562,60.742783 C37.4467295,61.7683498 36.2827889,62.2671815 35.2572221,61.8569548 C34.2316553,61.4467281 33.7328236,60.2827875 34.1430503,59.2572207 L37.2078224,51.5952903 C35.0156083,50.770172 32.8252834,49.7327143 30.6378199,48.4829173 L30.6378199,48.4829173 Z\" fill=\"#000000\" fill-rule=\"nonzero\"\/>\n          <\/g>\n        <\/svg>\n        <svg xmlns=\"http:\/\/www.w3.org\/2000\/svg\" version=\"1.1\" viewBox=\"-5.0 -10.0 110.0 135.0\" class=\"collapsible-icon open-icon\" style=\"display: none;\">\n          <path d=\"m78.195 48.906 6.4492-11.168-2.5977-1.5-6.207 10.75c-1.8398-1.4258-3.9844-2.9219-6.3867-4.3203l4.2422-11.66-2.8164-1.0273-4.0938 11.242c-1.9688-0.99219-4.0781-1.8828-6.2969-2.5938l2.1484-12.176-2.9531-0.51953-2.0977 11.887c-1.9648-0.46484-3.9961-0.77344-6.0859-0.875v-12.852h-3v12.852c-2.0898 0.10156-4.125 0.41016-6.0898 0.875l-2.0977-11.887-2.9531 0.51953 2.1484 12.176c-2.2148 0.71484-4.3242 1.6016-6.2969 2.5938l-4.0938-11.242-2.8203 1.0273 4.2422 11.66c-2.4023 1.3945-4.5469 2.8945-6.3867 4.3203l-6.207-10.75-2.5977 1.5 6.4492 11.168c-2.8164 2.4062-4.5078 4.2773-4.707 4.5l-0.88672 0.99609 0.88672 0.99609c0.60156 0.67578 14.883 16.504 32.902 16.504 18.02 0 32.301-15.828 32.902-16.504l0.88672-0.99609-0.88672-0.99609c-0.19141-0.21875-1.8828-2.0938-4.6992-4.5zm-57.898 5.5c2.3867-2.3984 9.0352-8.5312 17.664-12.004-3.0703 3.0781-4.9727 7.3242-4.9727 12.004 0 4.6758 1.8984 8.918 4.9648 11.996-8.6172-3.4727-15.27-9.6016-17.656-11.996zm29.703 14.008c-7.7266 0-14.012-6.2852-14.012-14.012 0-7.7266 6.2852-14.012 14.012-14.012s14.012 6.2852 14.012 14.012c0 7.7266-6.2852 14.012-14.012 14.012zm12.039-2.0039c3.0703-3.0781 4.9727-7.3242 4.9727-12.004 0-4.6758-1.8984-8.918-4.9648-11.996 8.6172 3.4727 15.27 9.6016 17.656 11.996-2.3867 2.3984-9.0352 8.5312-17.664 12.004z\"\/>\n          <path d=\"m54 53.332c-1.6172 0-2.9258-1.3086-2.9258-2.9258 0-1.6133 1.3047-2.9219 2.918-2.9258-1.1758-0.67969-2.5352-1.0742-3.9922-1.0742-4.418 0-8 3.582-8 8s3.582 8 8 8 8-3.582 8-8c0-1.457-0.39453-2.8164-1.0742-3.9922-0.003906 1.6133-1.3125 2.918-2.9258 2.918zm-4.6641 4.9062c-1.1055 0-2-0.89453-2-2s0.89453-2 2-2c1.1055 0 2 0.89453 2 2s-0.89844 2-2 2z\"\/>\n        <\/svg>\n      <\/button>\n      <div class=\"collapsible-content\">\n  \n        <div class=\"IngredientsIcons-wrapper\">\n          <div class=\"IngredientsIcons-content\">\n            <img src=\"https:\/\/cdn.shopify.com\/s\/files\/1\/0924\/0848\/0091\/files\/natural_icon_1.webp?v=1740426653\" alt=\"Cruelty-Free\" loading=\"lazy\">\n            <div class=\"IngredientsText\"><b> Naturel<\/b><\/div>\n          <\/div>\n          <div class=\"IngredientsIcons-content\">\n            <img src=\"https:\/\/cdn.shopify.com\/s\/files\/1\/0924\/0848\/0091\/files\/innovant_1.webp?v=1740426654\" alt=\"Vegan\" loading=\"lazy\">\n            <div class=\"IngredientsText\"><b>Formule<br>Inovante<\/b><\/div>\n          <\/div>\n          <div class=\"IngredientsIcons-content\">\n            <img src=\"https:\/\/cdn.shopify.com\/s\/files\/1\/0924\/0848\/0091\/files\/premium_ingredient_1.webp?v=1740426653\" alt=\"Sans Paraben\" loading=\"lazy\">\n            <div class=\"IngredientsText\"><b>Ingrédients<br> Premium<\/b><\/div>\n          <\/div>\n        <\/div>\n        <p id=\"pdp_ing\"><strong>Ingrédients de base :<\/strong>\nCyclopentasiloxane,Silice,Ozokérite\nPolyéthylène\nCire d'abeille\nDiméthicone\nTriméthylsiloxysilicate\nCire synthétique\nIsododécane\nÉthylhexylglycérine\nMéthylparabène\n<br>\n<br>\nContient également des ingrédients spécifiques par teinte.\n<br>\n<br>\n<a href=\"#shopify-section-template--25094752567643__faq_XAEkkP\"><strong><u>VOIR TOUT LES INGRÉDIENTS<\/u><\/strong><\/a>\n<br>\n<br>\n<\/p>\n      <\/div>\n    <\/div>\n\n    <div class=\"collapsible-wrapper\">\n      <button onclick=\"toggleSection(this)\" class=\"collapsible-item\">\n        RÉSULTATS CLINIQUE\n        <svg xmlns=\"http:\/\/www.w3.org\/2000\/svg\" xmlns:xlink=\"http:\/\/www.w3.org\/1999\/xlink\" viewBox=\"0 0 100 125\" version=\"1.1\" x=\"0px\" y=\"0px\" class=\"collapsible-icon closed-icon\">\n          <g stroke=\"none\" stroke-width=\"1\" fill=\"none\" fill-rule=\"evenodd\">\n            <path d=\"M30.6378199,48.4829173 L25.6000057,55.200003 C24.9372641,56.0836584 23.6836617,56.2627444 22.8000063,55.6000029 C21.9163509,54.9372613 21.7372649,53.6836589 22.4000064,52.8000035 L27.228789,46.3616267 C24.357763,44.4286582 21.4925541,42.1288216 18.6353708,39.4621172 C17.8278696,38.7084494 17.784229,37.4428719 18.5378968,36.6353708 C19.2915645,35.8278696 20.557142,35.784229 21.3646432,36.5378968 C40.5962252,54.4873733 59.4037748,54.4873733 78.6353568,36.5378968 C79.442858,35.784229 80.7084355,35.8278696 81.4621032,36.6353708 C82.215771,37.4428719 82.1721304,38.7084494 81.3646292,39.4621172 C78.5074459,42.1288216 75.642237,44.4286582 72.771211,46.3616267 L77.5999936,52.8000035 C78.2627351,53.6836589 78.0836491,54.9372613 77.1999937,55.6000029 C76.3163383,56.2627444 75.0627359,56.0836584 74.3999943,55.200003 L69.3621801,48.4829173 C67.1747166,49.7327143 64.9843917,50.770172 62.7921776,51.5952903 L65.8569497,59.2572207 C66.2671764,60.2827875 65.7683447,61.4467281 64.7427779,61.8569548 C63.7172111,62.2671815 62.5532705,61.7683498 62.1430438,60.742783 L58.972936,52.8175136 C56.6497244,53.4301738 54.3250274,53.8047648 52,53.9412865 L52,62 C52,63.1045706 51.1045692,64 50,64 C48.8954308,64 48,63.1045706 48,62 L48,53.9412865 C45.6749726,53.8047648 43.3502756,53.4301738 41.027064,52.8175136 L37.8569562,60.742783 C37.4467295,61.7683498 36.2827889,62.2671815 35.2572221,61.8569548 C34.2316553,61.4467281 33.7328236,60.2827875 34.1430503,59.2572207 L37.2078224,51.5952903 C35.0156083,50.770172 32.8252834,49.7327143 30.6378199,48.4829173 L30.6378199,48.4829173 Z\" fill=\"#000000\" fill-rule=\"nonzero\"\/>\n          <\/g>\n        <\/svg>\n        <svg xmlns=\"http:\/\/www.w3.org\/2000\/svg\" version=\"1.1\" viewBox=\"-5.0 -10.0 110.0 135.0\" class=\"collapsible-icon open-icon\" style=\"display: none;\">\n          <path d=\"m78.195 48.906 6.4492-11.168-2.5977-1.5-6.207 10.75c-1.8398-1.4258-3.9844-2.9219-6.3867-4.3203l4.2422-11.66-2.8164-1.0273-4.0938 11.242c-1.9688-0.99219-4.0781-1.8828-6.2969-2.5938l2.1484-12.176-2.9531-0.51953-2.0977 11.887c-1.9648-0.46484-3.9961-0.77344-6.0859-0.875v-12.852h-3v12.852c-2.0898 0.10156-4.125 0.41016-6.0898 0.875l-2.0977-11.887-2.9531 0.51953 2.1484 12.176c-2.2148 0.71484-4.3242 1.6016-6.2969 2.5938l-4.0938-11.242-2.8203 1.0273 4.2422 11.66c-2.4023 1.3945-4.5469 2.8945-6.3867 4.3203l-6.207-10.75-2.5977 1.5 6.4492 11.168c-2.8164 2.4062-4.5078 4.2773-4.707 4.5l-0.88672 0.99609 0.88672 0.99609c0.60156 0.67578 14.883 16.504 32.902 16.504 18.02 0 32.301-15.828 32.902-16.504l0.88672-0.99609-0.88672-0.99609c-0.19141-0.21875-1.8828-2.0938-4.6992-4.5zm-57.898 5.5c2.3867-2.3984 9.0352-8.5312 17.664-12.004-3.0703 3.0781-4.9727 7.3242-4.9727 12.004 0 4.6758 1.8984 8.918 4.9648 11.996-8.6172-3.4727-15.27-9.6016-17.656-11.996zm29.703 14.008c-7.7266 0-14.012-6.2852-14.012-14.012 0-7.7266 6.2852-14.012 14.012-14.012s14.012 6.2852 14.012 14.012c0 7.7266-6.2852 14.012-14.012 14.012zm12.039-2.0039c3.0703-3.0781 4.9727-7.3242 4.9727-12.004 0-4.6758-1.8984-8.918-4.9648-11.996 8.6172 3.4727 15.27 9.6016 17.656 11.996-2.3867 2.3984-9.0352 8.5312-17.664 12.004z\"\/>\n          <path d=\"m54 53.332c-1.6172 0-2.9258-1.3086-2.9258-2.9258 0-1.6133 1.3047-2.9219 2.918-2.9258-1.1758-0.67969-2.5352-1.0742-3.9922-1.0742-4.418 0-8 3.582-8 8s3.582 8 8 8 8-3.582 8-8c0-1.457-0.39453-2.8164-1.0742-3.9922-0.003906 1.6133-1.3125 2.918-2.9258 2.918zm-4.6641 4.9062c-1.1055 0-2-0.89453-2-2s0.89453-2 2-2c1.1055 0 2 0.89453 2 2s-0.89844 2-2 2z\"\/>\n        <\/svg>\n      <\/button>\n      <div class=\"collapsible-content\">\n<strong>Testé et approuvé : des résultats qui parlent d'eux-mêmes.<\/strong>\n<br>\n<br>\n\n        <div class=\"Product-bulletpoints-containerdesc\">\n          <div class=\"Product-bulletpointsAccordion\">\n            <div class=\"Product-bulletpointsAccordion-icon\">\n              <img src=\"https:\/\/cdn.shopify.com\/s\/files\/1\/0924\/0848\/0091\/files\/valid_badge_2.webp?v=1740600466\" alt=\"Description item 1\" loading=\"lazy\">\n            <\/div>\n            <div>\n              <span class=\"Product-bulletpointsAccordion-description\"><strong>96%<\/strong><\/span>\n              <span class=\"Product-bulletpointsAccordion-description2\">des femmes trouvent l'application plus fluide qu'avec leur ancien eyeliner.<\/span>\n            <\/div>\n          <\/div>\n          <div class=\"Product-bulletpointsAccordion\">\n            <div class=\"Product-bulletpointsAccordion-icon\">\n              <img src=\"https:\/\/cdn.shopify.com\/s\/files\/1\/0924\/0848\/0091\/files\/valid_badge_2.webp?v=1740600466\" alt=\"Description item 2\" loading=\"lazy\">\n            <\/div>\n            <div>\n              <span class=\"Product-bulletpointsAccordion-description\"><strong>91%<\/strong><\/span>\n              <span class=\"Product-bulletpointsAccordion-description2\">affirment que leur regard paraît plus défini et lifté.<\/span>\n            <\/div>\n          <\/div>\n          <div class=\"Product-bulletpointsAccordion\">\n            <div class=\"Product-bulletpointsAccordion-icon\">\n              <img src=\"https:\/\/cdn.shopify.com\/s\/files\/1\/0924\/0848\/0091\/files\/valid_badge_2.webp?v=1740600466\" alt=\"Description item 3\" loading=\"lazy\">\n            <\/div>\n            <div>\n              <span class=\"Product-bulletpointsAccordion-description\"><strong>87%<\/strong><\/span>\n              <span class=\"Product-bulletpointsAccordion-description2\">constatent une tenue impeccable 24h sans bavure.<\/span>\n            <\/div>\n          <\/div>\n          <div class=\"Product-bulletpointsAccordion\">\n            <div class=\"Product-bulletpointsAccordion-icon\">\n              <img src=\"https:\/\/cdn.shopify.com\/s\/files\/1\/0924\/0848\/0091\/files\/valid_badge_2.webp?v=1740600466\" alt=\"Description item 4\" loading=\"lazy\">\n            <\/div>\n            <div>\n              <span class=\"Product-bulletpointsAccordion-description\"><strong>94%<\/strong><\/span>\n              <span class=\"Product-bulletpointsAccordion-description2\">confirment une tolérance parfaite pour les yeux sensibles.<\/span>\n            <\/div>\n          <\/div>\n          <div class=\"Product-bulletpointsAccordion\">\n            <div class=\"Product-bulletpointsAccordion-icon\">\n              <img src=\"https:\/\/cdn.shopify.com\/s\/files\/1\/0924\/0848\/0091\/files\/valid_badge_2.webp?v=1740600466\" alt=\"Description item 5\" loading=\"lazy\">\n            <\/div>\n            <div>\n              <span class=\"Product-bulletpointsAccordion-description\"><strong>89%<\/strong><\/span>\n              <span class=\"Product-bulletpointsAccordion-description2\"> recommanderaient Luma Linea à une amie.<\/span>\n<br>\n<br>\n            <\/div>\n          <\/div>\n        <\/div>\n      <\/div>\n    <\/div>\n  <\/div>\n<\/div>\n\n\n\n<script>\n  function toggleSection(button) {\n    const content = button.nextElementSibling;\n    const closedIcon = button.querySelector('.closed-icon');\n    const openIcon = button.querySelector('.open-icon');\n    \n    if (content.style.maxHeight) {\n      content.style.maxHeight = null;\n      content.style.padding = \"0 1rem\";\n      closedIcon.style.display = \"inline-block\";\n      openIcon.style.display = \"none\";\n    } else {\n      content.style.maxHeight = content.scrollHeight + \"px\";\n      content.style.padding = \"1rem\";\n      closedIcon.style.display = \"none\";\n      openIcon.style.display = \"inline-block\";\n    }\n  }\n\n  function updateDeliveryEstimate() {\n    const today = new Date();\n    const fiveDaysLater = new Date(today.getTime() + 5 * 24 * 60 * 60 * 1000);\n    const twelveDaysLater = new Date(today.getTime() + 12 * 24 * 60 * 60 * 1000);\n\n    const formatDate = (date) => {\n      return date.toLocaleDateString(\"fr-FR\", { day: \"numeric\", month: \"long\" });\n    };\n\n    const deliveryEstimate = `Commandez le <span class=\"highlight\"><strong>${formatDate(today)}<\/strong><\/span> et recevez le entre le <span class=\"highlight\"><strong>${formatDate(fiveDaysLater)}<\/strong><\/span> et le <span class=\"highlight\"><strong>${formatDate(twelveDaysLater)}<\/strong><\/span>`;\n\n    document.getElementById(\"delivery-estimate\").innerHTML = deliveryEstimate;\n  }\n\n  function adjustLayout() {\n    const wrapper = document.getElementById(\"product-description-wrapper\");\n    if (window.innerWidth >= 768) {\n      wrapper.style.marginTop = \"-680px\";\n      wrapper.style.marginLeft = \"-20px\";\n    } else {\n      wrapper.style.marginTop = \"-35px\";\n      wrapper.style.marginLeft = \"0\";\n    }\n  }\n\n  document.addEventListener(\"DOMContentLoaded\", function() {\n    updateDeliveryEstimate();\n    adjustLayout();\n    window.addEventListener(\"resize\", adjustLayout);\n  });\n<\/script>\n\n<style>\n .Product-bulletpointsAccordion {\n    display: grid;\n    grid-template-columns: 32px auto;\n    margin-bottom: 10px;\n  }\n\n  .Product-bulletpointsAccordion-icon {\n    position: relative;\n    margin-bottom: auto;\n    width: 28px;\n  }\n\n  .Product-bulletpointsAccordion-icon img {\n    width: 25px;\n  }\n\n  .Product-bulletpointsAccordion-description,\n  .Product-bulletpointsAccordion-description2 {\n    font-size: 0.875rem;\n  }\n\n\n\n.IngredientsIcons-wrapper {\n  display: flex;\n  justify-content: center;\n  margin-bottom: 1rem;\n  gap: 2rem;\n}\n\n.IngredientsIcons-content {\n  display: flex;\n  flex-direction: column;\n  align-items: center;\n  text-align: center;\n}\n\n.IngredientsIcons-content img {\n  width: 50px;\n  height: 50px;\n  margin-bottom: 0.5rem;\n}\n\n.IngredientsText {\n  font-size: 0.75rem;\n}\n\n\n  .product-description-wrapper {\n    display: grid;\n    grid-template-columns: 1fr;\n    gap: 1rem;\n    margin-top: -35px;\n  }\n\n  .product-collapsible-description {\n    width: 100%;\n    position: relative;\n    margin: 0;\n    padding: 0;\n    overflow: visible;\n  }\n\n  .collapsible-wrapper {\n    border-top: 1px solid #e5e5e5;\n    margin-bottom: 5px;\n  }\n\n  .collapsible-wrapper:last-child {\n    border-bottom: 1px solid #e5e5e5;\n  }\n\n  .collapsible-item {\n    display: flex;\n    justify-content: space-between;\n    align-items: center;\n    width: 100%;\n    padding: 10px;\n    cursor: pointer;\n    background: none;\n    border: none;\n    text-align: left;\n    color: #111111;\n    background-color: #ffffff;\n    border-radius: 12px;\n    gap: 5px;\n  }\n\n  .collapsible-icon {\n    transition: transform 0.3s ease;\n    width: 40px;\n    height: 40px;\n  }\n\n  .collapsible-content {\n    padding: 0 1rem;\n    max-height: 0;\n    overflow: hidden;\n    transition: max-height 0.3s ease, padding 0.3s ease;\n  }\n\n  .highlight {\n    background-color: #fff8bc;\n    padding: 5px 10px;\n    display: inline-block;\n    margin-top: 10px;\n    text-align: center;\n    border-radius: 10px;\n  }\n\n  @media screen and (min-width: 1000px) {\n    .product-description-wrapper {\n      grid-template-columns: 1fr 1fr;\n      margin-top: -680px;\n      margin-left: -20px;\n    }\n\n    .product-collapsible-description {\n      position: sticky;\n      top: 20px;\n      align-self: start;\n    }\n  }\n<\/style>","background":"","background_gradient":"","text_color":""}},"video_atc_iyci8D":{"type":"video-atc","blocks":{"video_dcUDxi":{"type":"video","settings":{"video_url":"https:\/\/www.youtube.com\/watch?v=_9VUPq3SxOc&ab_channel=Shopify","poster":"shopify:\/\/shop_images\/11_a6338e94-f06e-45bd-8e49-b7ac8ce7dc57.webp","modal_heading":"<h4>Modal Heading<\/h4>","modal_text":"<p>Modal Text<\/p>"}},"video_KbgHm8":{"type":"video","settings":{"video_url":"https:\/\/www.youtube.com\/watch?v=_9VUPq3SxOc","poster":"shopify:\/\/shop_images\/11_a6338e94-f06e-45bd-8e49-b7ac8ce7dc57.webp","modal_heading":"<h4>Modal Heading<\/h4>","modal_text":"<p>Modal Text<\/p>"}},"video_8a6hmD":{"type":"video","settings":{"video_url":"https:\/\/www.youtube.com\/watch?v=_9VUPq3SxOc","poster":"shopify:\/\/shop_images\/11_a6338e94-f06e-45bd-8e49-b7ac8ce7dc57.webp","modal_heading":"<h4>Modal Heading<\/h4>","modal_text":"<p>Modal Text<\/p>"}},"video_HdRY97":{"type":"video","settings":{"video_url":"https:\/\/www.youtube.com\/watch?v=_9VUPq3SxOc","poster":"shopify:\/\/shop_images\/11_a6338e94-f06e-45bd-8e49-b7ac8ce7dc57.webp","modal_heading":"<h4>Modal Heading<\/h4>","modal_text":"<p>Modal Text<\/p>"}}},"block_order":["video_dcUDxi","video_KbgHm8","video_8a6hmD","video_HdRY97"],"disabled":true,"settings":{"videos_position":"below_buy","use_metafield":true,"heading":"","heading_custom":false,"heading_font":"josefin_sans_n4","heading_size":18,"heading_size_mobile":18,"heading_height":130,"heading_align":"center","heading_align_mobile":"center","slider_view":3,"slider_view_mobile":3,"slider_gap":16,"slider_gap_mobile":16,"slider_mt":20,"card_radius":10,"card_border_thickness":0,"card_shadow":true,"video_ratio":"portrait","video_ratio_mobile":"portrait","video_overlay":0.3,"icon_size":34,"icon_size_mobile":34,"icon_border_thickness":1,"icon_position_mobile":"bottom_left","icon_position":"bottom_left","hide_icon":false,"arrow_size":35,"arrow_size_mobile":35,"arrow_radius":5,"arrow_border_thickness":0,"arrow_hover_shadow":true,"arrow_show_desktop":true,"arrow_show_mobile":true,"show_content":false,"modal_width":30,"modal_width_mobile":95,"modal_padding_vertical":0,"modal_padding_vertical_mobile":0,"modal_padding_horizontal":0,"modal_padding_horizontal_mobile":0,"modal_radius":16,"modal_border_thickness":0,"modal_overlay":50,"close_size":42,"close_size_mobile":42,"close_radius":8,"close_border_thickness":0,"buttons_size":48,"buttons_size_mobile":48,"buttons_radius":8,"buttons_border_thickness":0,"modal_video_radius":0,"modal_video_border_thickness":0,"modal_video_ratio":"portrait","modal_video_ratio_mobile":"portrait","modal_heading_custom":false,"modal_heading_font":"josefin_sans_n4","modal_heading_size":28,"modal_heading_size_mobile":28,"modal_heading_height":130,"modal_heading_align":"center","modal_heading_align_mobile":"center","modal_text_custom":false,"modal_text_font":"josefin_sans_n4","modal_text_size":16,"modal_text_size_mobile":16,"modal_text_height":130,"modal_text_align":"center","modal_text_align_mobile":"center","modal_text_mt":16,"card_bg_color":"#ffffff","card_border_color":"#000000","card_shadow_color":"#000000","video_overlay_color":"#000000","icon_bg_color":"#000000","icon_border_color":"#ffffff","icon_color":"#ffffff","arrow_bg_color":"#ffffff","arrow_bg_hover_color":"#ffffff","arrow_border_color":"#000000","arrow_border_hover_color":"#000000","arrow_icon_color":"#1c1c1c","arrow_icon_hover_color":"#1c1c1c","modal_bg_color":"#ffffff","modal_border_color":"#000000","close_bg_color":"#ffffff","close_border_color":"#000000","close_icon_color":"#ffffff","buttons_bg_color":"#ffffff","buttons_border_color":"#000000","buttons_icon_color":"#ffffff","modal_video_border_color":"#000000","modal_content_bg_color":"#ffffff","modal_content_border_color":"#000000","modal_heading_color":"#000000","modal_text_color":"#000000","heading_color":"#000000","background_color":"#ffffff","background_gradient":"","border_color":"#000000","margin_top":0,"margin_bottom":0,"padding_top":20,"padding_bottom":20,"padding_horizontal":0,"padding_horizontal_mobile":0,"border_thickness":0,"lazy":true}},"scrolling_logo_neMHPf":{"type":"scrolling-logo","blocks":{"slide_Y4YUpj":{"type":"slide","settings":{"image":"shopify:\/\/shop_images\/elle.webp","link":"#id"}},"slide_PjJerg":{"type":"slide","settings":{"image":"shopify:\/\/shop_images\/cosmopolitan.webp","link":"#id"}},"slide_FQTgxV":{"type":"slide","settings":{"image":"shopify:\/\/shop_images\/people.webp","link":"#id"}},"slide_xrmyeE":{"type":"slide","settings":{"image":"shopify:\/\/shop_images\/glamour.webp","link":"#id"}}},"block_order":["slide_Y4YUpj","slide_PjJerg","slide_FQTgxV","slide_xrmyeE"],"settings":{"ss-title":"","heading_custom":false,"heading_font":"poppins_n4","header_size":30,"header_align":"center","scrolling_velocity":24,"pause_hover":false,"shadow":true,"sliders_mt":0,"logo_padding_top":24,"logo_padding_bottom":24,"slider_gap":20,"slider_gap_mobile":10,"slider_direction":"left","icon_width":300,"header_color":"#121212","border_color":"#cebced","background-color":"#ffffff","slider-background-color":"#cebced","margin_top":0,"margin_bottom":0,"padding_top":0,"padding_bottom":36,"full_width":true,"content_width":400,"border_thickness":0,"lazy":true}},"testimonials_reviews_luma_FpiYna":{"type":"testimonials-reviews-luma","blocks":{"testimonial_QhrBBM":{"type":"testimonial","settings":{"slide_image":"shopify:\/\/shop_images\/RV_V2.webp","customer_name":"Claudine","customer_age":"52 ans","rating":5,"testimonial_text":"\"Avant, tracer une ligne nette était un cauchemar, surtout avec mes paupières ridées. Maintenant, l’eyeliner glisse facilement et le résultat est impeccable dès le premier essai. Une vraie révolution pour mes 55 ans !\""}},"testimonial_BmCqnF":{"type":"testimonial","settings":{"slide_image":"shopify:\/\/shop_images\/RV_V2_1.webp","customer_name":"Isabelle","customer_age":"55 ans","rating":5,"testimonial_text":"Je n’arrivais jamais à garder un trait d’eyeliner net toute la journée. Avec Luma Linea, même après 10 heures, aucun transfert ni bavure. Mon regard reste intense jusqu’au soir sans aucune retouche ! C'est devenu ma marque de référence."}},"testimonial_z4qmHW":{"type":"testimonial","settings":{"slide_image":"shopify:\/\/shop_images\/RV_V2_3.webp","customer_name":"Sylvie","customer_age":"58 ans","rating":5,"testimonial_text":"\"Je pensais devoir abandonner l’eyeliner à cause des ridules sur mes paupières… Mais celui-ci les lisse sans les marquer et donne vraiment un effet liftant. J’ai retrouvé confiance en mon maquillage à 58 ans.\""}},"testimonial_QpC4ah":{"type":"testimonial","settings":{"slide_image":"shopify:\/\/shop_images\/RV_V2_4.webp","customer_name":"Nathalie","customer_age":"51 ans","rating":5,"testimonial_text":"\"J’ai toujours eu les yeux sensibles, et les autres eyeliners me provoquaient des rougeurs et larmes. Avec Luma Linea, aucune irritation, même après plusieurs heures. Enfin un produit pensé pour nous.\""}}},"block_order":["testimonial_QhrBBM","testimonial_BmCqnF","testimonial_z4qmHW","testimonial_QpC4ah"],"settings":{"heading":"Un regard sublimé en un seul trait.","highlighted_text":"un seul","highlight_color":"#a98ad8","badge_image":"shopify:\/\/shop_images\/BADGE_N1_EYELINER_V2.webp","cta_text":"Le dernier eyeliner que vous porterez - et que vous adorerez."}},"eyeliner_carrousel_VzzcYY":{"type":"eyeliner-carrousel","blocks":{"eyeliner_FVNY3m":{"type":"eyeliner","settings":{"name":"NOIR","color":"Intensité Élégante","description":"Accentue le contraste et crée un regard profond et sophistiqué. Idéal pour un effet chic et intense.","finish":"Noir","image":"shopify:\/\/shop_images\/LIGHT_BLUE_EYES_Dark_Eyeliner.webp","show_mesmerise_badge":false,"product_id":"","variant_noir":"50102382264667","variant_bois":"50102382297435","variant_saphir":"50102382330203","variant_emeraude":"50102382362971","variant_mocha":"50102382395739","variant_fumee":"50102382428507","variant_doree":"50102382461275","variant_cuivre":"50102382494043","eye_color_blue":true,"eye_color_brown":false,"eye_color_dark_brown":false,"eye_color_green":false,"skin_tone_light":true,"skin_tone_medium":false,"skin_tone_dark":false}},"eyeliner_q9Hz6p":{"type":"eyeliner","settings":{"name":"BOIS","color":"Chaleur Naturelle","description":"Un brun chaud qui adoucit le regard tout en le définissant naturellement. Parfait pour un effet subtil et élégant.","finish":"Bois","image":"shopify:\/\/shop_images\/LIGHT_BLUE_EYES_Bois_EYELINER.webp","show_mesmerise_badge":false,"product_id":"","variant_noir":"50102382264667","variant_bois":"50102382297435","variant_saphir":"50102382330203","variant_emeraude":"50102382362971","variant_mocha":"50102382395739","variant_fumee":"50102382428507","variant_doree":"50102382461275","variant_cuivre":"50102382494043","eye_color_blue":true,"eye_color_brown":false,"eye_color_dark_brown":false,"eye_color_green":false,"skin_tone_light":true,"skin_tone_medium":false,"skin_tone_dark":false}},"eyeliner_FjEfff":{"type":"eyeliner","settings":{"name":"SAPHIR","color":"Éclat Captivant","description":"Le bleu intense crée un effet monochrome qui sublime les yeux bleus et ajoute une touche vibrante.","finish":"Saphir","image":"shopify:\/\/shop_images\/LIGHT_BLUE_EYES_Saphir_EYELINER.webp","show_mesmerise_badge":false,"product_id":"","variant_noir":"50102382264667","variant_bois":"50102382297435","variant_saphir":"50102382330203","variant_emeraude":"50102382362971","variant_mocha":"50102382395739","variant_fumee":"50102382428507","variant_doree":"50102382461275","variant_cuivre":"50102382494043","eye_color_blue":true,"eye_color_brown":false,"eye_color_dark_brown":false,"eye_color_green":false,"skin_tone_light":true,"skin_tone_medium":false,"skin_tone_dark":false}},"eyeliner_adDr4D":{"type":"eyeliner","settings":{"name":"ÉMERAUDE","color":"Élégance Vibrante","description":"Un vert profond qui rehausse la luminosité des iris clairs et apporte un éclat original.","finish":"Émeraude","image":"shopify:\/\/shop_images\/LIGHT_BLUE_EYES_emeraud_EYELINER.webp","show_mesmerise_badge":false,"product_id":"","variant_noir":"50102382264667","variant_bois":"50102382297435","variant_saphir":"50102382330203","variant_emeraude":"50102382362971","variant_mocha":"50102382395739","variant_fumee":"50102382428507","variant_doree":"50102382461275","variant_cuivre":"50102382494043","eye_color_blue":true,"eye_color_brown":false,"eye_color_dark_brown":false,"eye_color_green":false,"skin_tone_light":true,"skin_tone_medium":false,"skin_tone_dark":false}},"eyeliner_TL4P3J":{"type":"eyeliner","settings":{"name":"MOCHA","color":"Raffinement Subtil","description":"Un brun froid qui apporte de la définition sans durcir les traits, idéal pour un look naturel.","finish":"Mocha","image":"shopify:\/\/shop_images\/LIGHT_BLUE_EYES_mocha_EYELINER.webp","show_mesmerise_badge":true,"product_id":"","variant_noir":"50102382264667","variant_bois":"50102382297435","variant_saphir":"50102382330203","variant_emeraude":"50102382362971","variant_mocha":"50102382395739","variant_fumee":"50102382428507","variant_doree":"50102382461275","variant_cuivre":"50102382494043","eye_color_blue":true,"eye_color_brown":false,"eye_color_dark_brown":false,"eye_color_green":false,"skin_tone_light":true,"skin_tone_medium":false,"skin_tone_dark":false}},"eyeliner_cLWfLA":{"type":"eyeliner","settings":{"name":"FUMÉE","color":"Sophistication Moderne","description":"Un gris profond élégant qui adoucit et illumine les yeux bleus sans durcir le regard.","finish":"Fumée","image":"shopify:\/\/shop_images\/LIGHT_BLUE_EYES_Fumee_EYELINER.webp","show_mesmerise_badge":true,"product_id":"","variant_noir":"50102382264667","variant_bois":"50102382297435","variant_saphir":"50102382330203","variant_emeraude":"50102382362971","variant_mocha":"50102382395739","variant_fumee":"50102382428507","variant_doree":"50102382461275","variant_cuivre":"50102382494043","eye_color_blue":true,"eye_color_brown":false,"eye_color_dark_brown":false,"eye_color_green":false,"skin_tone_light":true,"skin_tone_medium":false,"skin_tone_dark":false}},"eyeliner_W9LNey":{"type":"eyeliner","settings":{"name":"DORÉE","color":"Lumière et Éclat","description":"Apporte de la lumière et illumine les yeux bleus pour un effet doux et rayonnant.","finish":"Dorée","image":"shopify:\/\/shop_images\/LIGHT_BLUE_EYES_Doree_EYELINER.webp","show_mesmerise_badge":false,"product_id":"","variant_noir":"50102382264667","variant_bois":"50102382297435","variant_saphir":"50102382330203","variant_emeraude":"50102382362971","variant_mocha":"50102382395739","variant_fumee":"50102382428507","variant_doree":"50102382461275","variant_cuivre":"50102382494043","eye_color_blue":true,"eye_color_brown":false,"eye_color_dark_brown":false,"eye_color_green":false,"skin_tone_light":true,"skin_tone_medium":false,"skin_tone_dark":false}},"eyeliner_7NxJGU":{"type":"eyeliner","settings":{"name":"CUIVRE","color":"Chaleur et Intensity","description":"Crée un contraste chaleureux qui fait ressortir la vivacité du bleu et ajoute une touche ensoleillée.","finish":"Cuivre","image":"shopify:\/\/shop_images\/LIGHT_BLUE_EYES_Cuivre_EYELINER.webp","show_mesmerise_badge":false,"product_id":"","variant_noir":"50102382264667","variant_bois":"50102382297435","variant_saphir":"50102382330203","variant_emeraude":"50102382362971","variant_mocha":"50102382395739","variant_fumee":"50102382428507","variant_doree":"50102382461275","variant_cuivre":"50102382494043","eye_color_blue":true,"eye_color_brown":false,"eye_color_dark_brown":false,"eye_color_green":false,"skin_tone_light":true,"skin_tone_medium":false,"skin_tone_dark":false}},"eyeliner_zach3j":{"type":"eyeliner","settings":{"name":"NOIR","color":"Intensité Élégante","description":"Crée un contraste intense qui fait ressortir la profondeur et la vivacité des yeux verts.","finish":"Noir","image":"shopify:\/\/shop_images\/GREEN_EYES_black_eyeliner.webp","show_mesmerise_badge":true,"product_id":"","variant_noir":"50102382264667","variant_bois":"50102382297435","variant_saphir":"50102382330203","variant_emeraude":"50102382362971","variant_mocha":"50102382395739","variant_fumee":"50102382428507","variant_doree":"50102382461275","variant_cuivre":"50102382494043","eye_color_blue":false,"eye_color_brown":false,"eye_color_dark_brown":false,"eye_color_green":true,"skin_tone_light":true,"skin_tone_medium":false,"skin_tone_dark":false}},"eyeliner_f78idK":{"type":"eyeliner","settings":{"name":"BOIS","color":"Chaleur Naturelle","description":"Un brun chaud qui équilibre l’intensité des yeux verts et rehausse leur éclat naturel","finish":"Bois","image":"shopify:\/\/shop_images\/GREEN_EYES_Bois_eyeliner.webp","show_mesmerise_badge":true,"product_id":"","variant_noir":"50102382264667","variant_bois":"50102382297435","variant_saphir":"50102382330203","variant_emeraude":"50102382362971","variant_mocha":"50102382395739","variant_fumee":"50102382428507","variant_doree":"50102382461275","variant_cuivre":"50102382494043","eye_color_blue":false,"eye_color_brown":false,"eye_color_dark_brown":false,"eye_color_green":true,"skin_tone_light":true,"skin_tone_medium":false,"skin_tone_dark":false}},"eyeliner_M7Ayim":{"type":"eyeliner","settings":{"name":"SAPHIR","color":"Éclat Captivant","description":"Apporte une touche originale et inattendue qui intensifie l’éclat du vert.","finish":"Saphir","image":"shopify:\/\/shop_images\/GREEN_EYES_sahpir_eyeliner.webp","show_mesmerise_badge":false,"product_id":"","variant_noir":"50102382264667","variant_bois":"50102382297435","variant_saphir":"50102382330203","variant_emeraude":"50102382362971","variant_mocha":"50102382395739","variant_fumee":"50102382428507","variant_doree":"50102382461275","variant_cuivre":"50102382494043","eye_color_blue":false,"eye_color_brown":false,"eye_color_dark_brown":false,"eye_color_green":true,"skin_tone_light":true,"skin_tone_medium":false,"skin_tone_dark":false}},"eyeliner_WPM6aA":{"type":"eyeliner","settings":{"name":"ÉMERAUDE","color":"Élégance Vibrante","description":"Une teinte parfaite pour jouer sur les nuances et donner encore plus de profondeur aux yeux verts.","finish":"Émeraude","image":"shopify:\/\/shop_images\/GREEN_EYES_Emeraud_eyeliner.webp","show_mesmerise_badge":false,"product_id":"","variant_noir":"50102382264667","variant_bois":"50102382297435","variant_saphir":"50102382330203","variant_emeraude":"50102382362971","variant_mocha":"50102382395739","variant_fumee":"50102382428507","variant_doree":"50102382461275","variant_cuivre":"50102382494043","eye_color_blue":false,"eye_color_brown":false,"eye_color_dark_brown":false,"eye_color_green":true,"skin_tone_light":true,"skin_tone_medium":false,"skin_tone_dark":false}},"eyeliner_NWc9MA":{"type":"eyeliner","settings":{"name":"MOCHA","color":"Raffinement Subtil","description":"Complémente naturellement les sous-tons dorés et noisette des yeux verts.","finish":"Mocha","image":"shopify:\/\/shop_images\/GREEN_EYES_Mocha_eyeliner.webp","show_mesmerise_badge":false,"product_id":"","variant_noir":"50102382264667","variant_bois":"50102382297435","variant_saphir":"50102382330203","variant_emeraude":"50102382362971","variant_mocha":"50102382395739","variant_fumee":"50102382428507","variant_doree":"50102382461275","variant_cuivre":"50102382494043","eye_color_blue":false,"eye_color_brown":false,"eye_color_dark_brown":false,"eye_color_green":true,"skin_tone_light":true,"skin_tone_medium":false,"skin_tone_dark":false}},"eyeliner_TYkUKQ":{"type":"eyeliner","settings":{"name":"FUMÉE","color":"Sophistication Moderne","description":"Un gris profond qui contraste élégamment avec les yeux verts pour un regard sophistiqué.","finish":"Fumée","image":"shopify:\/\/shop_images\/GREEN_EYES_Grey_eyeliner.webp","show_mesmerise_badge":false,"product_id":"","variant_noir":"50102382264667","variant_bois":"50102382297435","variant_saphir":"50102382330203","variant_emeraude":"50102382362971","variant_mocha":"50102382395739","variant_fumee":"50102382428507","variant_doree":"50102382461275","variant_cuivre":"50102382494043","eye_color_blue":false,"eye_color_brown":false,"eye_color_dark_brown":false,"eye_color_green":true,"skin_tone_light":true,"skin_tone_medium":false,"skin_tone_dark":false}},"eyeliner_mnntH3":{"type":"eyeliner","settings":{"name":"DORÉE","color":"Lumière et Éclat","description":"Un éclat doré qui illumine subtilement les yeux verts et adoucit leur intensité naturelle.","finish":"Dorée","image":"shopify:\/\/shop_images\/GREEN_EYES_Doree_eyeliner.webp","show_mesmerise_badge":false,"product_id":"","variant_noir":"50102382264667","variant_bois":"50102382297435","variant_saphir":"50102382330203","variant_emeraude":"50102382362971","variant_mocha":"50102382395739","variant_fumee":"50102382428507","variant_doree":"50102382461275","variant_cuivre":"50102382494043","eye_color_blue":false,"eye_color_brown":false,"eye_color_dark_brown":false,"eye_color_green":true,"skin_tone_light":true,"skin_tone_medium":false,"skin_tone_dark":false}},"eyeliner_7y9p9m":{"type":"eyeliner","settings":{"name":"CUIVRE","color":"Chaleur et Intensity","description":"Accentue la richesse des yeux verts et les rend encore plus lumineux et captivants.","finish":"Cuivre","image":"shopify:\/\/shop_images\/GREEN_EYES_Cuivre_eyeliner.webp","show_mesmerise_badge":false,"product_id":"","variant_noir":"50102382264667","variant_bois":"50102382297435","variant_saphir":"50102382330203","variant_emeraude":"50102382362971","variant_mocha":"50102382395739","variant_fumee":"50102382428507","variant_doree":"50102382461275","variant_cuivre":"50102382494043","eye_color_blue":false,"eye_color_brown":false,"eye_color_dark_brown":false,"eye_color_green":true,"skin_tone_light":true,"skin_tone_medium":false,"skin_tone_dark":false}},"eyeliner_zAAXDD":{"type":"eyeliner","settings":{"name":"NOIR","color":"Intensité Élégante","description":"Structure le regard avec intensité et profondeur, parfait pour un look défini et sophistiqué.","finish":"Noir","image":"shopify:\/\/shop_images\/CHATAIN_EYES_black_eyeliner.webp","show_mesmerise_badge":false,"product_id":"","variant_noir":"50102382264667","variant_bois":"50102382297435","variant_saphir":"50102382330203","variant_emeraude":"50102382362971","variant_mocha":"50102382395739","variant_fumee":"50102382428507","variant_doree":"50102382461275","variant_cuivre":"50102382494043","eye_color_blue":false,"eye_color_brown":true,"eye_color_dark_brown":false,"eye_color_green":false,"skin_tone_light":true,"skin_tone_medium":false,"skin_tone_dark":false}},"eyeliner_KDrYpx":{"type":"eyeliner","settings":{"name":"BOIS","color":"Chaleur Naturelle","description":"Complémente les reflets ambrés et dorés des yeux châtain pour un effet naturel et équilibré.","finish":"Bois","image":"shopify:\/\/shop_images\/CHATAIN_EYES_bois_eyeliner.webp","show_mesmerise_badge":true,"product_id":"","variant_noir":"50102382264667","variant_bois":"50102382297435","variant_saphir":"50102382330203","variant_emeraude":"50102382362971","variant_mocha":"50102382395739","variant_fumee":"50102382428507","variant_doree":"50102382461275","variant_cuivre":"50102382494043","eye_color_blue":false,"eye_color_brown":true,"eye_color_dark_brown":false,"eye_color_green":false,"skin_tone_light":true,"skin_tone_medium":false,"skin_tone_dark":false}},"eyeliner_XRccGz":{"type":"eyeliner","settings":{"name":"SAPHIR","color":"Éclat Captivant","description":"Ajoute une touche originale et lumineuse, idéal pour faire pétiller le regard.","finish":"Saphir","image":"shopify:\/\/shop_images\/CHATAIN_EYES_blue_eyeliner.webp","show_mesmerise_badge":false,"product_id":"","variant_noir":"50102382264667","variant_bois":"50102382297435","variant_saphir":"50102382330203","variant_emeraude":"50102382362971","variant_mocha":"50102382395739","variant_fumee":"50102382428507","variant_doree":"50102382461275","variant_cuivre":"50102382494043","eye_color_blue":false,"eye_color_brown":true,"eye_color_dark_brown":false,"eye_color_green":false,"skin_tone_light":true,"skin_tone_medium":false,"skin_tone_dark":false}},"eyeliner_eziHAy":{"type":"eyeliner","settings":{"name":"ÉMERAUDE","color":"Élégance Vibrante","description":"Sublime les sous-tons dorés des yeux châtain et renforce leur intensité naturelle.","finish":"Émeraude","image":"shopify:\/\/shop_images\/CHATAIN_EYES_emeraud_eyeliner.webp","show_mesmerise_badge":true,"product_id":"","variant_noir":"50102382264667","variant_bois":"50102382297435","variant_saphir":"50102382330203","variant_emeraude":"50102382362971","variant_mocha":"50102382395739","variant_fumee":"50102382428507","variant_doree":"50102382461275","variant_cuivre":"50102382494043","eye_color_blue":false,"eye_color_brown":true,"eye_color_dark_brown":false,"eye_color_green":false,"skin_tone_light":true,"skin_tone_medium":false,"skin_tone_dark":false}},"eyeliner_jTpw4M":{"type":"eyeliner","settings":{"name":"MOCHA","color":"Raffinement Subtil","description":"Un brun froid parfait pour structurer sans alourdir, idéal pour un maquillage quotidien.","finish":"Mocha","image":"shopify:\/\/shop_images\/CHATAIN_EYES_mocha_eyeliner.webp","show_mesmerise_badge":false,"product_id":"","variant_noir":"50102382264667","variant_bois":"50102382297435","variant_saphir":"50102382330203","variant_emeraude":"50102382362971","variant_mocha":"50102382395739","variant_fumee":"50102382428507","variant_doree":"50102382461275","variant_cuivre":"50102382494043","eye_color_blue":false,"eye_color_brown":true,"eye_color_dark_brown":false,"eye_color_green":false,"skin_tone_light":true,"skin_tone_medium":false,"skin_tone_dark":false}},"eyeliner_qLrY3a":{"type":"eyeliner","settings":{"name":"FUMÉE","color":"Sophistication Moderne","description":"Un gris profond qui met en valeur les nuances noisette des iris avec une touche de modernité.","finish":"Fumée","image":"shopify:\/\/shop_images\/CHATAIN_EYES_fumee_eyeliner.webp","show_mesmerise_badge":false,"product_id":"","variant_noir":"50102382264667","variant_bois":"50102382297435","variant_saphir":"50102382330203","variant_emeraude":"50102382362971","variant_mocha":"50102382395739","variant_fumee":"50102382428507","variant_doree":"50102382461275","variant_cuivre":"50102382494043","eye_color_blue":false,"eye_color_brown":true,"eye_color_dark_brown":false,"eye_color_green":false,"skin_tone_light":true,"skin_tone_medium":false,"skin_tone_dark":false}},"eyeliner_Miceq9":{"type":"eyeliner","settings":{"name":"DORÉE","color":"Lumière et Éclat","description":"Apporte une touche de lumière et accentue la richesse des tons châtain.","finish":"Dorée","image":"shopify:\/\/shop_images\/CHATAIN_EYES_doree_eyeliner.webp","show_mesmerise_badge":false,"product_id":"","variant_noir":"50102382264667","variant_bois":"50102382297435","variant_saphir":"50102382330203","variant_emeraude":"50102382362971","variant_mocha":"50102382395739","variant_fumee":"50102382428507","variant_doree":"50102382461275","variant_cuivre":"50102382494043","eye_color_blue":false,"eye_color_brown":true,"eye_color_dark_brown":false,"eye_color_green":false,"skin_tone_light":true,"skin_tone_medium":false,"skin_tone_dark":false}},"eyeliner_e4BK94":{"type":"eyeliner","settings":{"name":"CUIVRE","color":"Chaleur et Intensity","description":"Un éclat cuivré qui réchauffe et illumine les yeux châtains pour un effet lumineux naturel.","finish":"Cuivre","image":"shopify:\/\/shop_images\/CHATAIN_EYES_cuivre_eyeliner.webp","show_mesmerise_badge":false,"product_id":"","variant_noir":"50102382264667","variant_bois":"50102382297435","variant_saphir":"50102382330203","variant_emeraude":"50102382362971","variant_mocha":"50102382395739","variant_fumee":"50102382428507","variant_doree":"50102382461275","variant_cuivre":"50102382494043","eye_color_blue":false,"eye_color_brown":true,"eye_color_dark_brown":false,"eye_color_green":false,"skin_tone_light":true,"skin_tone_medium":false,"skin_tone_dark":false}},"eyeliner_g7zqhe":{"type":"eyeliner","settings":{"name":"NOIR","color":"Intensité Élégante","description":"Intensifie et magnifie le regard, offrant une profondeur hypnotique et élégante.","finish":"Noir","image":"shopify:\/\/shop_images\/BRUN_EYES_Black_eyeliner.webp","show_mesmerise_badge":false,"product_id":"","variant_noir":"50102382264667","variant_bois":"50102382297435","variant_saphir":"50102382330203","variant_emeraude":"50102382362971","variant_mocha":"50102382395739","variant_fumee":"50102382428507","variant_doree":"50102382461275","variant_cuivre":"50102382494043","eye_color_blue":false,"eye_color_brown":false,"eye_color_dark_brown":true,"eye_color_green":false,"skin_tone_light":true,"skin_tone_medium":false,"skin_tone_dark":false}},"eyeliner_CUCL7Q":{"type":"eyeliner","settings":{"name":"BOIS","color":"Chaleur Naturelle","description":"Un brun terreux qui souligne naturellement les yeux bruns et intensifie leur profondeur subtile.","finish":"Bois","image":"shopify:\/\/shop_images\/BRUN_EYES_Bois_eyeliner.webp","show_mesmerise_badge":false,"product_id":"","variant_noir":"50102382264667","variant_bois":"50102382297435","variant_saphir":"50102382330203","variant_emeraude":"50102382362971","variant_mocha":"50102382395739","variant_fumee":"50102382428507","variant_doree":"50102382461275","variant_cuivre":"50102382494043","eye_color_blue":false,"eye_color_brown":false,"eye_color_dark_brown":true,"eye_color_green":false,"skin_tone_light":true,"skin_tone_medium":false,"skin_tone_dark":false}},"eyeliner_p8bL7z":{"type":"eyeliner","settings":{"name":"SAPHIR","color":"Éclat Captivant","description":"Contraste avec les tons bruns et ajoute une touche audacieuse et moderne.","finish":"Saphir","image":"shopify:\/\/shop_images\/BRUN_EYES_Saphir_eyeliner.webp","show_mesmerise_badge":true,"product_id":"","variant_noir":"50102382264667","variant_bois":"50102382297435","variant_saphir":"50102382330203","variant_emeraude":"50102382362971","variant_mocha":"50102382395739","variant_fumee":"50102382428507","variant_doree":"50102382461275","variant_cuivre":"50102382494043","eye_color_blue":false,"eye_color_brown":false,"eye_color_dark_brown":true,"eye_color_green":false,"skin_tone_light":true,"skin_tone_medium":false,"skin_tone_dark":false}},"eyeliner_RLF9gn":{"type":"eyeliner","settings":{"name":"ÉMERAUDE","color":"Élégance Vibrante","description":"Complémente parfaitement les sous-tons chauds des yeux bruns et illumine le regard.","finish":"Émeraude","image":"shopify:\/\/shop_images\/BRUN_EYES_Emeraud_eyeliner.webp","show_mesmerise_badge":false,"product_id":"","variant_noir":"50102382264667","variant_bois":"50102382297435","variant_saphir":"50102382330203","variant_emeraude":"50102382362971","variant_mocha":"50102382395739","variant_fumee":"50102382428507","variant_doree":"50102382461275","variant_cuivre":"50102382494043","eye_color_blue":false,"eye_color_brown":false,"eye_color_dark_brown":true,"eye_color_green":false,"skin_tone_light":true,"skin_tone_medium":false,"skin_tone_dark":false}},"eyeliner_hiA8pP":{"type":"eyeliner","settings":{"name":"MOCHA","color":"Raffinement Subtil","description":"Un brun froid parfait pour structurer sans alourdir, idéal pour un maquillage quotidien.","finish":"Mocha","image":"shopify:\/\/shop_images\/BRUN_EYES_Mocha_eyeliner.webp","show_mesmerise_badge":true,"product_id":"","variant_noir":"50102382264667","variant_bois":"50102382297435","variant_saphir":"50102382330203","variant_emeraude":"50102382362971","variant_mocha":"50102382395739","variant_fumee":"50102382428507","variant_doree":"50102382461275","variant_cuivre":"50102382494043","eye_color_blue":false,"eye_color_brown":false,"eye_color_dark_brown":true,"eye_color_green":false,"skin_tone_light":true,"skin_tone_medium":false,"skin_tone_dark":false}},"eyeliner_E9CLiN":{"type":"eyeliner","settings":{"name":"FUMÉE","color":"Sophistication Moderne","description":"Un gris profond qui met en valeur les nuances noisette des iris avec une touche de modernité.","finish":"Fumée","image":"shopify:\/\/shop_images\/BRUN_EYES_Fumee_eyeliner.webp","show_mesmerise_badge":false,"product_id":"","variant_noir":"50102382264667","variant_bois":"50102382297435","variant_saphir":"50102382330203","variant_emeraude":"50102382362971","variant_mocha":"50102382395739","variant_fumee":"50102382428507","variant_doree":"50102382461275","variant_cuivre":"50102382494043","eye_color_blue":false,"eye_color_brown":false,"eye_color_dark_brown":true,"eye_color_green":false,"skin_tone_light":true,"skin_tone_medium":false,"skin_tone_dark":false}},"eyeliner_rk4eNE":{"type":"eyeliner","settings":{"name":"DORÉE","color":"Lumière et Éclat","description":"Rehausse la chaleur des yeux bruns en apportant un éclat subtil et lumineux.","finish":"Dorée","image":"shopify:\/\/shop_images\/BRUN_EYES_Doree_eyeliner.webp","show_mesmerise_badge":false,"product_id":"","variant_noir":"50102382264667","variant_bois":"50102382297435","variant_saphir":"50102382330203","variant_emeraude":"50102382362971","variant_mocha":"50102382395739","variant_fumee":"50102382428507","variant_doree":"50102382461275","variant_cuivre":"50102382494043","eye_color_blue":false,"eye_color_brown":false,"eye_color_dark_brown":true,"eye_color_green":false,"skin_tone_light":true,"skin_tone_medium":false,"skin_tone_dark":false}},"eyeliner_qGKHaM":{"type":"eyeliner","settings":{"name":"CUIVRE","color":"Chaleur et Intensity","description":"Accentue la richesse des iris foncés et leur donne un effet ensoleillé et éclatant.","finish":"Cuivre","image":"shopify:\/\/shop_images\/BRUN_EYES_Cuivre_eyeliner.webp","show_mesmerise_badge":false,"product_id":"","variant_noir":"50102382264667","variant_bois":"50102382297435","variant_saphir":"50102382330203","variant_emeraude":"50102382362971","variant_mocha":"50102382395739","variant_fumee":"50102382428507","variant_doree":"50102382461275","variant_cuivre":"50102382494043","eye_color_blue":false,"eye_color_brown":false,"eye_color_dark_brown":true,"eye_color_green":false,"skin_tone_light":true,"skin_tone_medium":false,"skin_tone_dark":false}}},"block_order":["eyeliner_FVNY3m","eyeliner_q9Hz6p","eyeliner_FjEfff","eyeliner_adDr4D","eyeliner_TL4P3J","eyeliner_cLWfLA","eyeliner_W9LNey","eyeliner_7NxJGU","eyeliner_zach3j","eyeliner_f78idK","eyeliner_M7Ayim","eyeliner_WPM6aA","eyeliner_NWc9MA","eyeliner_TYkUKQ","eyeliner_mnntH3","eyeliner_7y9p9m","eyeliner_zAAXDD","eyeliner_KDrYpx","eyeliner_XRccGz","eyeliner_eziHAy","eyeliner_jTpw4M","eyeliner_qLrY3a","eyeliner_Miceq9","eyeliner_e4BK94","eyeliner_g7zqhe","eyeliner_CUCL7Q","eyeliner_p8bL7z","eyeliner_RLF9gn","eyeliner_hiA8pP","eyeliner_E9CLiN","eyeliner_rk4eNE","eyeliner_qGKHaM"],"settings":{"title":"Trouvez la teinte parfaite."}},"solution_luma_WFNtW8":{"type":"solution-luma","blocks":{"benefit_MQKTmh":{"type":"benefit","settings":{"icon":"shopify:\/\/shop_images\/APPLI.webp","title":"Application ultra fluide, zéro tirallement","description":"Grâce à sa texture gel-crème unique, il glisse\nsans effort même sur les paupières les plus\ndélicates. Fini les traits irréguliers et les bavures."}},"benefit_xLqcGr":{"type":"benefit","settings":{"icon":"shopify:\/\/shop_images\/WATERPROOF.webp","title":"Une tenue parfaite, toute la journée","description":"Résistant à l’eau et à l’humidité, il reste impeccable\ndu matin au soir, sans coulures ni retouches.\nUn regard intense, sans effort."}},"benefit_GHTJQj":{"type":"benefit","settings":{"icon":"shopify:\/\/shop_images\/hyppo.webp","title":"Conçue pour les yeux sensibles","description":"Testé sous contrôle ophtalmologique, \nhypoallergénique et enrichi en agents protecteurs, \nil respecte votre peau et évite rougeurs et irritations."}},"benefit_mretFU":{"type":"benefit","settings":{"icon":"shopify:\/\/shop_images\/gel_cream.webp","title":"Un tracé précis, modulable et intense","description":"Sa mine ultra-crémeuse permet un dessin précis, \nmodulable selon vos envies : un effet naturel ou \nun regard audacieux en un seul geste."}}},"block_order":["benefit_MQKTmh","benefit_xLqcGr","benefit_GHTJQj","benefit_mretFU"],"settings":{"main_title":"Pourquoi 90% des eyeliners classiques ne conviennent plus après 50 ans ?","intro_text":"Après 50 ans, votre peau change... mais pas les eyeliners ! Conçus pour des paupières lisses, ils tirent sur la peau fragile, marquent les ridules et disparaissent en quelques heures. Il est temps d'adopter un eyeliner pensé pour vous.","product_image":"shopify:\/\/shop_images\/EYELINER.webp","hero_image":"shopify:\/\/shop_images\/PHOTO_MOCHA_copie.webp","benefits_image":"shopify:\/\/shop_images\/Photo_Plusieurs_femmes_Luma.webp","secondary_title":"Enfin, un eyeliner pensé pour VOUS !"}},"etape_luma_AT9eAb":{"type":"etape-luma","blocks":{"step_peEWNp":{"type":"step","settings":{"image":"shopify:\/\/shop_images\/ETAPE_1.webp","text":"<p><strong>Tracer la première ligne guide <\/strong> Suivez la ligne naturelle de vos cils et remontez légèrement vers l’arc du sourcil pour un effet liftant.<\/p>"}},"step_ADdwNT":{"type":"step","settings":{"image":"shopify:\/\/shop_images\/ETAPES_2.webp","text":"<p><strong>Former la structure du trait<\/strong>  Reliez le coin externe à la base des cils en dessinant un petit \"V\" pour sculpter le regard.<\/p>"}},"step_CCh7Yi":{"type":"step","settings":{"image":"shopify:\/\/shop_images\/ETAPE_3.webp","text":"<p><strong>Compléter le tracé<\/strong> Remplissez l'intérieur des tracés pour un fini intense et homogène.<\/p>"}},"step_fTwQhX":{"type":"step","settings":{"image":"shopify:\/\/shop_images\/ETAPE_4.webp","text":"<p><strong>Estomper et ajuster si besoin<\/strong> Floutez les contours pour un rendu plus doux ou intensifiez selon votre style.<\/p>"}}},"block_order":["step_peEWNp","step_ADdwNT","step_CCh7Yi","step_fTwQhX"],"custom_css":[".steps-button-template--25094752567643__etape_luma_AT9eAb {margin-top: 10px; background-color: #a58fcb; color: #ffffff; border: none; cursor: pointer; max-width: 500px; border-radius: 12px; font-size: 18px; font-weight: bold; transition: background-color 0.3sease; padding: 0.9rem 0.9rem; width: 100%;}"],"settings":{"heading":"<h2><strong>Un tracé parfait en 4 étapes simples.<\/strong><\/h2>","heading_custom":true,"heading_font":"poppins_n6","heading_size":40,"heading_size_mobile":36,"heading_height":110,"heading_align":"left","heading_align_mobile":"left","body_gap":50,"body_gap_mobile":56,"body_mt":72,"body_mt_mobile":30,"use_slider":true,"slider_view_mobile":1.1,"slider_gap_mobile":20,"image_radius":0,"image_border_thickness":2,"image_ratio":"square","image_ratio_mobile":"square","circle_number_size":40,"circle_number_size_mobile":44,"number_custom":true,"number_font":"poppins_n4","number_size":18,"number_size_mobile":18,"text_custom":true,"text_font":"poppins_n4","text_size":18,"text_size_mobile":18,"text_height":130,"text_mt":24,"text_align":"center","text_align_mobile":"center","button":"AJOUTER AU PANIER","button_url":"#bundleSelector","button_custom":true,"button_font":"poppins_n6","button_size":16,"button_size_mobile":18,"button_height":170,"button_width":300,"button_width_mobile":325,"button_mt":70,"button_mt_mobile":32,"button_padding_vertical":14,"button_padding_vertical_mobile":14,"button_padding_horizontal":22,"button_padding_horizontal_mobile":22,"button_radius":14,"button_border_thickness":0,"button_align":"center","button_align_mobile":"center","button_style":"non_outline","image_border_color":"#342c40","circle_number_bg_color":"#f0e7ff","number_color":"#4d435c","text_color":"#342c40","button_color":"#ffffff","button_hover_color":"#ffffff","button_bg_color":"#8d6fbd","button_bg_hover_color":"#8d6fbd","button_border_color":"#000000","button_border_hover_color":"#000000","heading_color":"#342c40","background_color":"#ffffff","background_gradient":"","border_color":"#000000","margin_top":0,"margin_bottom":0,"padding_top":36,"padding_bottom":36,"padding_horizontal":5,"padding_horizontal_mobile":1.5,"full_width":false,"content_width":90,"border_thickness":0,"lazy":true}},"testimonial_luma_wJCgfx":{"type":"testimonial-luma","blocks":{"image_UNjiJY":{"type":"image","settings":{"image":"shopify:\/\/shop_images\/151612_6889263726615_93ba94d8_5f45_4620_8bf3_865eb9748352.webp"}},"image_6R39YC":{"type":"image","settings":{"image":"shopify:\/\/shop_images\/714uOSamptL.webp"}},"image_XJC7zc":{"type":"image","settings":{"image":"shopify:\/\/shop_images\/REVIEWS_LUMA.webp"}},"image_ahEDwg":{"type":"image","settings":{"image":"shopify:\/\/shop_images\/dc83ef_ce465e778cd6422b8c84a9a75.webp"}},"testimonial_4AniEf":{"type":"testimonial","settings":{"rating":5,"text":"Je trouvais le prix un peu élevé au début, mais après l’avoir essayé, je comprends mieux. La qualité et la tenue justifient largement l'investissement. Je recommande à 100%.","author":"Martine M.","verified":"ACHAT VERIFIÉ"}},"testimonial_AjydnN":{"type":"testimonial","settings":{"rating":4.5,"text":"J'avais abandonné l'idée d'utiliser un eyeliner. Mes paupières ridées rendaient chaque application compliquée. Avec celui-ci, tout glisse en douceur, sans tiraillement. Une vraie révélation.","author":"Christine K.","verified":"ACHAT VERIFIÉ"}},"testimonial_pG3mNG":{"type":"testimonial","settings":{"rating":5,"text":"Même après une journée entière à courir partout, le tracé reste net. Plus besoin de retouches toutes les heures, il tient vraiment 24 heures comme promis.","author":"Cécile B.","verified":"ACHAT VERIFIÉ"}},"testimonial_4TTqDR":{"type":"testimonial","settings":{"rating":4.5,"text":"J'ai les yeux très sensibles, et la plupart des eyeliners me provoquent des rougeurs. Celui-ci est incroyablement doux, je peux enfin sublimer mon regard sans irritation.","author":"Béatrice S.","verified":"ACHAT VERIFIÉ"}},"testimonial_X6wDtn":{"type":"testimonial","settings":{"rating":5,"text":"Avec le temps, mon regard semblait fatigué. Cet eyeliner redonne un effet liftant immédiat. Je me sens rajeunie, et mes amies me demandent mon secret !","author":"Patricia I.","verified":"ACHAT VERIFIÉ"}},"testimonial_JpczPD":{"type":"testimonial","settings":{"rating":4.5,"text":"Mes yeux ont tendance à larmoyer facilement, et je finissais toujours avec des bavures. Là, aucune coulure, même sous la pluie. Bluffant de tenue.","author":"Hélène A.","verified":"ACHAT VERIFIÉ"}}},"block_order":["image_UNjiJY","image_6R39YC","image_XJC7zc","image_ahEDwg","testimonial_4AniEf","testimonial_AjydnN","testimonial_pG3mNG","testimonial_4TTqDR","testimonial_X6wDtn","testimonial_JpczPD"],"settings":{"hide_images":true,"heading":"<h2>Des milliers de femmes convaincues après 50 ans.<\/h2>","heading_custom":true,"heading_font":"poppins_n7","heading_size":40,"heading_size_mobile":36,"heading_height":110,"heading_align":"left","heading_align_mobile":"left","layout":"image_testimonial","layout_mobile":"image_testimonial","layout_gap":34,"layout_gap_mobile":28,"layout_mt":36,"image_row":"2","image_row_mobile":"2","image_gap":12,"image_gap_mobile":10,"image_radius":0,"image_border_thickness":0,"image_ratio":"square","testimonials_style_mobile":"slider","testimonials_row":"2","testimonials_row_mobile":"1","testimonials_gap":12,"testimonials_gap_mobile":12,"testimonial_padding_vertical":12,"testimonial_padding_horizontal":12,"testimonial_radius":8,"testimonial_border_thickness":1,"stars_size":18,"testimonial_text_custom":true,"testimonial_text_font":"poppins_n4","testimonial_text_size":16,"testimonial_text_size_mobile":16,"testimonial_text_height":140,"testimonial_text_mt":8,"testimonial_author_custom":false,"testimonial_author_font":"josefin_sans_n4","testimonial_author_size":14,"testimonial_author_size_mobile":14,"testimonial_author_height":150,"testimonial_author_mt":12,"testimonial_verified_custom":false,"testimonial_verified_font":"josefin_sans_n4","testimonial_verified_size":10,"testimonial_verified_size_mobile":10,"testimonial_verified_height":150,"button":"AJOUTER AU PANIER","button_url":"#bundleSelector","button_use_icon":false,"button_custom":true,"button_font":"poppins_n7","button_size":22,"button_size_mobile":18,"button_height":150,"button_align":"center","button_align_mobile":"center","button_mt":4,"button_padding_vertical":16,"button_padding_horizontal":50,"button_radius":12,"button_border_thickness":2,"heading_color":"#342c40","background_color":"#ffffff","background_gradient":"","border_color":"#342c40","button_color":"#ffffff","button_hover_color":"#ffffff","button_bg_color":"#a58fcb","button_bg_hover_color":"#8d6fbd","button_border_color":"rgba(0,0,0,0)","button_border_hover_color":"rgba(0,0,0,0)","image_border_color":"#000000","testimonial_bg_color":"#ffffff","testimonial_border_color":"#4d435c","stars_color":"#9f87c7","testimonial_text_color":"#000000","testimonial_author_color":"#342c40","testimonial_verified_color":"#4d435c","testimonial_pagination_color":"#000000","margin_top":0,"margin_bottom":0,"padding_top":52,"padding_bottom":68,"padding_horizontal":5,"padding_horizontal_mobile":1.5,"content_width":90,"border_thickness":0}},"whyusnotother_LNUqab":{"type":"whyusnotother","blocks":{"compare_header_nYL9cx":{"type":"compare_header","settings":{"logo":"shopify:\/\/shop_images\/LUMA-PHOTO-PRODUIT-V3-FIN-PNG.webp","heading":"Luma Linea"}},"compare_header_9cXyRR":{"type":"compare_header","settings":{"logo":"shopify:\/\/shop_images\/eyeliner_classique_2.webp","heading":"Eyeliner Classique"}},"compare_price_PhWrMV":{"type":"compare_price","settings":{"heading":"Tenue","active_price_1":"24H, résiste à tout","active_price_2":"4H, s'efface vite","active_price_3":"","active_price_4":"","active_price_5":"","active_price_6":""}},"compare_price_jj4nXH":{"type":"compare_price","settings":{"heading":"Application","active_price_1":"Application fluide, sans effort","active_price_2":"Difficile, accroche","active_price_3":"$0","active_price_4":"$0","active_price_5":"$0","active_price_6":"$0"}},"compare_price_WFjNCr":{"type":"compare_price","settings":{"heading":"Texture","active_price_1":"Gel-crème, glisse parfaitement","active_price_2":"Sec, accroche la peau","active_price_3":"$0","active_price_4":"$0","active_price_5":"$0","active_price_6":"$0"}},"compare_price_MghPbp":{"type":"compare_price","settings":{"heading":"Précision","active_price_1":"Pointe précise, tracé net","active_price_2":"Tracé irrégulier","active_price_3":"$0","active_price_4":"$0","active_price_5":"$0","active_price_6":"$0"}},"compare_price_VDrth7":{"type":"compare_price","settings":{"heading":"Pigmentation","active_price_1":"Couleur intense au premier trait","active_price_2":"Couleur fade","active_price_3":"$0","active_price_4":"$0","active_price_5":"$0","active_price_6":"$0"}}},"block_order":["compare_header_nYL9cx","compare_header_9cXyRR","compare_price_PhWrMV","compare_price_jj4nXH","compare_price_WFjNCr","compare_price_MghPbp","compare_price_VDrth7"],"settings":{"heading":"Pourquoi se contenter de moins bien ?","heading_size":40,"heading_weight":"700","heading_color":"#342c40","heading_font":"poppins_n7","heading_size_mobile":36,"heading_weight_mobile":"700","subheading":"Choisissez Luma: Tenue 6x plus longue, application 100% plus fluide, couleur intense en un seul passage.","subheading_size":18,"subheading_weight":"400","subheading_color":"#0d0d0d","subheading_font":"poppins_n4","subheading_size_mobile":16,"subheading_weight_mobile":"400","compare_text_color":"#4d435c","compare_text_size":20,"compare_text_weight":"400","compare_text_font":"poppins_n4","compare_background":"#ffffff","compare_background_active":"#f0e7ff","compare_text_color_active":"#342c40","compare_text_size_mobile":12,"compare_text_weight_mobile":"400","compare_radius":4,"enable_logo_border":false,"logo_border_size":4,"logo_border_color":"#342c40","logo_border_style":"solid","vs_bg_color":"#342c40","vs_text_color":"#f0e7ff","line_color":"#4d435c","line_size":1,"line_style":"dashed","bottom_text":"","bottom_text_size":12,"bottom_text_weight":"400","bottom_text_color":"#afabab","bottom_text_font":"josefin_sans_n4","bottom_text_size_mobile":10,"bottom_text_weight_mobile":"400","layout_margin_top":0,"layout_margin_bottom":0,"layout_width":true}},"custom_liquid_rdFyMT":{"type":"custom-liquid","disabled":true,"settings":{"full_width":true,"remove_vertical_spacing":false,"remove_horizontal_spacing":false,"liquid":"<div class=\"product-reviews-section\">\n  <div class=\"reviews-container\">\n    <h2 class=\"section-title\">\n      <span class=\"ivy-mode\">What<\/span> SundayFeels Users Are Saying\n    <\/h2>\n    <p class=\"subtitle\">Where every review tells a story of confidence regained and sweat conquered.<\/p>\n    \n    <div class=\"reviews-content\">\n      <div class=\"overall-rating\">\n        <div class=\"rating-number\">4.8<\/div>\n        <div class=\"stars\">\n          {% for i in (1..5) %}\n            <svg class=\"star-icon\" width=\"24\" height=\"24\" viewBox=\"0 0 24 24\" fill=\"none\" xmlns=\"http:\/\/www.w3.org\/2000\/svg\">\n              <path d=\"M12 2L15.09 8.26L22 9.27L17 14.14L18.18 21.02L12 17.77L5.82 21.02L7 14.14L2 9.27L8.91 8.26L12 2Z\" fill=\"#434461\" stroke=\"#434461\" stroke-width=\"2\" stroke-linecap=\"round\" stroke-linejoin=\"round\"\/>\n            <\/svg>\n          {% endfor %}\n        <\/div>\n        <p class=\"review-count\">Based on 5,453 reviews<\/p>\n      <\/div>\n      \n      <div class=\"rating-details\">\n        {% assign ratings = \"EFFICACY,CONVENIENCE,SCENT,EFFICACY DURATION,VALUE FOR MONEY\" | split: \",\" %}\n        {% assign rating_values = \"4.9,4.6,4.7,4.8,4.6\" | split: \",\" %}\n        \n        {% for rating in ratings %}\n          <div class=\"rating-item\">\n            <span class=\"rating-name\">{{ rating }}<\/span>\n            <div class=\"rating-stars\">\n              {% assign rating_value = rating_values[forloop.index0] | times: 1 %}\n              {% for i in (1..5) %}\n                <svg class=\"star-icon\" width=\"16\" height=\"16\" viewBox=\"0 0 24 24\" fill=\"none\" xmlns=\"http:\/\/www.w3.org\/2000\/svg\">\n                  <path d=\"M12 2L15.09 8.26L22 9.27L17 14.14L18.18 21.02L12 17.77L5.82 21.02L7 14.14L2 9.27L8.91 8.26L12 2Z\" fill=\"{% if i <= rating_value %}#434461{% else %}#E5E5E5{% endif %}\" stroke=\"{% if i <= rating_value %}#434461{% else %}#E5E5E5{% endif %}\" stroke-width=\"2\" stroke-linecap=\"round\" stroke-linejoin=\"round\"\/>\n                <\/svg>\n              {% endfor %}\n              <span class=\"rating-value\">{{ rating_value }}<\/span>\n            <\/div>\n          <\/div>\n        {% endfor %}\n      <\/div>\n    <\/div>\n  <\/div>\n<\/div>\n\n<style>\n  @import url('https:\/\/fonts.googleapis.com\/css2?family=Poppins:ital,wght@0,400;0,600;1,400;1,600&display=swap');\n  @import url('https:\/\/fonts.googleapis.com\/css2?family=Ivy+Mode&display=swap');\n\n  .product-reviews-section {\n    font-family: 'Poppins', sans-serif;\n    background-color: #FAF7E4;\n    padding: 4rem 0;\n    width: 100vw;\n    position: relative;\n    left: 50%;\n    right: 50%;\n    margin-left: -50vw;\n    margin-right: -50vw;\nmargin-bottom: -70px;\n  }\n\n  .reviews-container {\n    max-width: 1200px;\n    margin: 0 auto;\n    padding: 0 2rem;\n  }\n\n  .section-title {\n    font-size: 45px;\n    font-weight: normal;\n    text-align: center;\n    margin-bottom: -8px;\n    font-style: italic;\ncolor: #434461;\n  }\n\n  .ivy-mode {\n    font-family: 'Ivy Mode', serif;\nfont-weight: bold;\nfont-size: 60px;\n  }\n\n  .subtitle {\n    text-align: center;\n    color: #1A1A1A;\n    margin-bottom: 90px;\n  }\n\n  .reviews-content {\n    display: flex;\n    justify-content: space-between;\n    align-items: flex-start;\nmargin-right: 125px\n  }\n\n  .overall-rating {\n    text-align: center;\n    flex: 1;\n  }\n\n  .rating-number {\n    font-size: 3rem;\n    font-weight: bold;\n    margin-bottom: 0.5rem;\n  }\n\n  .stars {\n    display: flex;\n    justify-content: center;\n    margin-bottom: 0.5rem;\n  }\n\n  .star-icon {\n    width: 1.5rem;\n    height: 1.5rem;\n  }\n\n  .review-count {\n    font-size: 0.875rem;\n    color: #4B5563;\n  }\n\n  .rating-details {\n    flex: 2;\n    margin-left: 2rem;\n  }\n\n  .rating-item {\n    display: flex;\n    justify-content: space-between;\n    align-items: center;\n    margin-bottom: 0.5rem;\n  }\n\n  .rating-name {\n    font-size: 0.875rem;\n    font-weight: 500;\n    text-transform: uppercase;\n  }\n\n  .rating-stars {\n    display: flex;\n    align-items: center;\n  }\n\n  .rating-value {\n    font-size: 0.875rem;\n    font-weight: 500;\n    margin-left: 0.5rem;\n  }\n\n  @media screen and (max-width: 767px) {\n    .product-reviews-section {\n      padding: 2rem 0;\nmargin-bottom: 15px;\n    }\n\n.reviews-content {\nmargin-right: 0;\n\n}\n\n.section-title {\n    font-size: 30px;\n    font-weight: ;\n    text-align: center;\n    margin-bottom: 8px;\n    font-style: italic;\ncolor: #434461;\n  }\n\n  .ivy-mode {\n    font-family: 'Ivy Mode', serif;\nfont-size: 45px;\n  }\n\n  .subtitle {\n    text-align: center;\n    color: #1A1A1A;\nfont-size: 14px;\n    margin-bottom: 35px;\n  }\n\n\n\n    .reviews-content {\n      flex-direction: column;\n      align-items: center;\n    }\n\n    .rating-details {\n      margin-left: 0;\n      margin-top: 2rem;\n      width: 100%;\n    }\n  }\n\n<\/style>","background":"","background_gradient":"","text_color":""}},"1741028793a3e89977":{"type":"apps","blocks":{"trustoo_io_reviews_review_widget_Y7Hn4R":{"type":"shopify:\/\/apps\/trustoo-io-reviews\/blocks\/review-widget\/c8f15077-6475-4e86-ad06-b66038d5ba2c","settings":{}}},"block_order":["trustoo_io_reviews_review_widget_Y7Hn4R"],"settings":{"full_width":true,"remove_vertical_spacing":false,"remove_horizontal_spacing":false,"background":"","background_gradient":"","text_color":"","enable_review_integration":true,"review_header_gradient":"linear-gradient(135deg, rgba(255, 194, 102, 1), rgba(255, 163, 26, 1) 100%)","review_header_text_color":"#000000","review_button_background":"#000000","review_button_text_color":"#ffffff"}},"faq_XAEkkP":{"type":"faq","blocks":{"item_3XCmbb":{"type":"item","settings":{"title":"Luma Linea est-il un liquide ou un crayon ?","content":"<p>Luma Linea a une texture unique de gel-crème. Il se comporte comme un crayon. Il est facile à tenir, à appliquer et à manipuler. Il ne bouge pas. Mais il dépose les pigments comme un liquide - en lignes nettes, claires et précises. Généreux, vibrant, soyeux.<\/p>"}},"item_dziVW4":{"type":"item","settings":{"title":"Puis-je l'appliquer sur ma ligne d'eau ?","content":"<p>Luma Linea est hypoallergénique. Sans danger pour votre paupière et vos cils. <\/p><p>Avec un pH équilibré pour les yeux sensibles, il est conçu pour se loger dans votre ligne d'eau. Mais soyez un consommateur conscient et avisé. Faites passer votre santé avant tout et effectuez des tests épicutanés sur tous les produits. <\/p><p>Cessez d'utiliser le produit s'il provoque une irritation.<\/p>"}},"item_BhcQLg":{"type":"item","settings":{"title":"Quels sont les ingrédients contenus dans Luma Linea ?","content":"<p>Voici la liste complète des ingrédients qui entrent dans la composition de Luma Linea :<br\/><br\/><strong>Luma Linea Eyeliner. Noir<\/strong><br\/><br\/>Cyclopentasiloxane, Silice, Ozokérite, Polyéthylène, Cire d'abeille, Diméthicone, Trimethylsiloxysilicate, CI 77499, CI 77491, CI 77492, CI 77266, Cire synthétique, Isododécane, Mica, Triethoxycaprylylsilane, Ethylhexylglycérine, Methylparaben.<br\/><br\/><strong>Luma Linea Eyeliner. Bois<\/strong><br\/><br\/>Cyclopentasiloxane, silice, ozokérite, polyéthylène, cire d'abeille, diméthicone, triméthylsiloxysilicate, CI 77491, CI 77492, CI 77499, CI 77266, cire synthétique, isododécane, mica, triéthoxycaprylylsilane, éthylhexylglycérine, méthylparabène.<br\/><br\/><strong>Luma Linea Eyeliner. Saphir<\/strong><br\/><br\/>Cyclopentasiloxane, silice, ozokérite, polyéthylène, cire d'abeille, diméthicone, triméthylsiloxysilicate, CI 77491, CI 77492, CI 77266, CI 42090, CI 77499, mica, triéthoxycaprylylsilane, cire synthétique, isododécane, éthylhexylglycérine, méthylparabène.<br\/><br\/><strong>Luma Linea Eyeliner. Émeraude<br\/><\/strong><br\/>Cyclopentasiloxane, silice, ozokérite, polyéthylène, cire d'abeille, diméthicone, triméthylsiloxysilicate, CI77492, CI77499, CI77491, CI77288, Ci77266, cire synthétique, isododécane, mica, triéthoxycaprylylsilane, éthylhexylglycérine, méthylparabène.<br\/><br\/><strong>Luma Linea Eyeliner. Fumée<\/strong><br\/><br\/>Cyclopentasiloxane, silice, ozokérite, polyéthylène, cire d'abeille, diméthicone, triméthylsiloxysilicate, CI77492, CI77499, CI77491, CI77266, cire synthétique, isododécane, mica, triéthoxycaprylylsilane, éthylhexylglycérine, méthylparabène.<br\/><br\/><strong>Luma Linea Eyeliner. Dorée<\/strong><br\/><br\/>Cyclopentasiloxane, borosilicate de calcium et d'aluminium, fluorphlogopite synthétique, silice, ozokérite, polyéthylène, cire d'abeille, diméthicone, triméthylsiloxysilicate, cire synthétique, isododécane, CI 77891, oxyde d'étain, éthylhexylglycérine, méthylparabène.<br\/><br\/><strong>Luma Linea Eyeliner. Cuivre<\/strong><br\/><br\/>Cyclopentasiloxane, silice, ozokérite, polyéthylène, cire d'abeille, mica, CI 77491, diméthicone, triméthylsiloxysilicate, fluorphlogopite synthétique, CI 77891, cire synthétique, isododécane, éthylhexylglycérine, méthylparabène.<br\/><br\/><strong>Luma Linea Eyeliner. Mocha<\/strong><br\/><br\/>Cyclopentasiloxane, Silice, Ozokerite, Fluorphlogopite synthétique, Polyéthylène, Cire d'abeille, CI 77491, Mica, Diméthicone, Trimethylsiloxysilicate, Cire synthétique, Isododecane, CI 77891, Ethylhexylglycérine, Methylparaben.<\/p>"}},"item_AbjgWY":{"type":"item","settings":{"title":"J'ai les yeux sensibles. Puis-je porter Luma Linea ?","content":"<p>Oui, étant donné que son pH est équilibré et qu'il est hypoallergénique, il peut être utilisé en toute sécurité autour des yeux. Même si vous avez les yeux sensibles à cause d'allergies ou de médicaments.<\/p>"}},"item_EgPLdR":{"type":"item","settings":{"title":"L'embout se cassera-t-il si l'élément tombe ?","content":"<p>Manipulez votre Luma Linea avec précaution. L'embout est renforcé et protégé par le boîtier dans lequel il se trouve. Il est crémeux mais ne se casse pas aussi facilement que certains autres liners légers.<\/p>"}},"item_ibeNBr":{"type":"item","settings":{"title":"L'embout est-il rétractable ?","content":"<p>Non, la pointe n'est pas rétractable. Les eyeliners rétractables jouent souvent à cache-cache avec le volume de produit que vous obtenez. <br\/><br\/>Avec Luma Linea, ce n'est pas de la poudre aux yeux. Ce que vous voyez est ce que vous obtenez. Aiguiser la pointe pour une précision longue durée et durable !<\/p>"}},"item_YnbicP":{"type":"item","settings":{"title":"Combien de fois dois-je renouveler l'application de Luma linea dans la journée ?","content":"<p>93% des testeuses ont trouvé que l'application initiale de Luma Linea durait toute la journée. Mais cela varie d'une reine à l'autre, en fonction de l'intensité de la couche initiale, du degré de sébum de la paupière et de l'humidité de l'air. <br\/><br\/>Ce que nous pouvons dire, c'est que plus vous utiliserez cet eyeliner, plus vos cils et vos paupières se développeront.<\/p>"}},"item_dirVQM":{"type":"item","settings":{"title":"Luma Linea est-il résistant à l'eau ?","content":"<p>Luma Linea est résistant à l'eau. Il n'utilise pas de cires ou de fibres lourdes pour s'accrocher à votre paupière et à vos cils. Au contraire, il repousse l'humidité. <br\/><br\/>L'huile et l'eau ne se mélangent pas.<br\/><br\/>Ce principe permet d'obtenir des pigments intenses et durables. <\/p>"}},"item_QFRTNR":{"type":"item","settings":{"title":"Je porte des lentilles de contact. Puis-je utiliser Luma Linea ?","content":"<p>Bien sûr. Luma Linea est un produit doux au toucher qui n'irrite pas les yeux... même si vous portez des lentilles de contact.<\/p>"}}},"block_order":["item_3XCmbb","item_dziVW4","item_BhcQLg","item_AbjgWY","item_EgPLdR","item_ibeNBr","item_YnbicP","item_dirVQM","item_QFRTNR"],"custom_css":["{margin-top: 30px;}"],"settings":{"full_width":true,"subheading":"","title":"FOIRE AUX QUESTIONS","content":"","team_avatar_width":200,"support_hours":"","answer_time":"","button_text":"","button_url":"shopify:\/\/pages\/contact","text_position":"center","background":"rgba(0,0,0,0)","background_gradient":"","text_color":"rgba(0,0,0,0)","heading_color":"","heading_gradient":"","button_background":"","button_text_color":"rgba(0,0,0,0)","accordion_background":"#ffffff","accordion_text_color":""}}},"order":["custom_liquid_aLrwHi","main","custom_liquid_eHAcky","video_atc_iyci8D","scrolling_logo_neMHPf","testimonials_reviews_luma_FpiYna","eyeliner_carrousel_VzzcYY","solution_luma_WFNtW8","etape_luma_AT9eAb","testimonial_luma_wJCgfx","whyusnotother_LNUqab","custom_liquid_rdFyMT","1741028793a3e89977","faq_XAEkkP"]}